Workbook

Sheet Шкалы
A1: Дилер | B1: Тип | C1: Раздел | D1: Категория | E1: Таблица | F1: Показатель | G1: № строки | H1: Итог | I1: Тир | J1: № тира | K1: Тир от | L1: Тир до | M1: Значение | N1: Единица | O1: Вкладка (была) | P1: Ячейка в исходнике | Q1: Ключ: строка | R1: Ключ: тир | S1: Ключ: значение | T1: Ключ: порядок строки | U1: Ключ: итог | V1: Ключ: колонка плана
A2: КОМПО Технолоджис | B2: РФ | C2: План | D2: Итого по дилеру | E2: План и бонусы | F2: Выручка 2024 | G2: 1 | J2: 1 | M2: 4164812 | N2: EUR | O2: КТ | P2: D4 | Q2: =A2&"|"&C2&"|"&D2&"|"&G2 -> КОМПО Технолоджис|План|Итого по дилеру|1 | R2: =A2&"|"&C2&"|"&D2&"|"&J2 -> КОМПО Технолоджис|План|Итого по дилеру|1 | S2: =A2&"|"&C2&"|"&D2&"|"&G2&"|"&J2 -> КОМПО Технолоджис|План|Итого по дилеру|1|1 | T2: =A2&"|"&C2&"|"&G2 -> КОМПО Технолоджис|План|1 | U2: =IF(H2="да",A2&"|"&C2&"|"&D2&"|"&J2,"") | V2: =IF(C2="План",A2&"|"&J2,"") -> КОМПО Технолоджис|1
A3: КОМПО Технолоджис | B3: РФ | C3: План | D3: Итого по дилеру | E3: План и бонусы | F3: Выручка 2025 | G3: 1 | J3: 2 | M3: 4121760 | N3: EUR | O3: КТ | P3: E4 | Q3: =A3&"|"&C3&"|"&D3&"|"&G3 -> КОМПО Технолоджис|План|Итого по дилеру|1 | R3: =A3&"|"&C3&"|"&D3&"|"&J3 -> КОМПО Технолоджис|План|Итого по дилеру|2 | S3: =A3&"|"&C3&"|"&D3&"|"&G3&"|"&J3 -> КОМПО Технолоджис|План|Итого по дилеру|1|2 | T3: =A3&"|"&C3&"|"&G3 -> КОМПО Технолоджис|План|1 | U3: =IF(H3="да",A3&"|"&C3&"|"&D3&"|"&J3,"") | V3: =IF(C3="План",A3&"|"&J3,"") -> КОМПО Технолоджис|2
A4: КОМПО Технолоджис | B4: РФ | C4: План | D4: Итого по дилеру | E4: План и бонусы | F4: План 2026 | G4: 1 | J4: 3 | M4: 4142912 | N4: EUR | O4: КТ | P4: F4 | Q4: =A4&"|"&C4&"|"&D4&"|"&G4 -> КОМПО Технолоджис|План|Итого по дилеру|1 | R4: =A4&"|"&C4&"|"&D4&"|"&J4 -> КОМПО Технолоджис|План|Итого по дилеру|3 | S4: =A4&"|"&C4&"|"&D4&"|"&G4&"|"&J4 -> КОМПО Технолоджис|План|Итого по дилеру|1|3 | T4: =A4&"|"&C4&"|"&G4 -> КОМПО Технолоджис|План|1 | U4: =IF(H4="да",A4&"|"&C4&"|"&D4&"|"&J4,"") | V4: =IF(C4="План",A4&"|"&J4,"") -> КОМПО Технолоджис|3
A5: КОМПО Технолоджис | B5: РФ | C5: План | D5: Итого по дилеру | E5: План и бонусы | F5: Прирост П/Ф | G5: 1 | J5: 4 | M5: 0.0051317859 | N5: % | O5: КТ | P5: G4 | Q5: =A5&"|"&C5&"|"&D5&"|"&G5 -> КОМПО Технолоджис|План|Итого по дилеру|1 | R5: =A5&"|"&C5&"|"&D5&"|"&J5 -> КОМПО Технолоджис|План|Итого по дилеру|4 | S5: =A5&"|"&C5&"|"&D5&"|"&G5&"|"&J5 -> КОМПО Технолоджис|План|Итого по дилеру|1|4 | T5: =A5&"|"&C5&"|"&G5 -> КОМПО Технолоджис|План|1 | U5: =IF(H5="да",A5&"|"&C5&"|"&D5&"|"&J5,"") | V5: =IF(C5="План",A5&"|"&J5,"") -> КОМПО Технолоджис|4
A6: КОМПО Технолоджис | B6: РФ | C6: План | D6: Сервис | E6: План и бонусы | F6: Выручка 2024 | G6: 2 | J6: 1 | M6: 346883 | N6: EUR | O6: КТ | P6: D5 | Q6: =A6&"|"&C6&"|"&D6&"|"&G6 -> КОМПО Технолоджис|План|Сервис|2 | R6: =A6&"|"&C6&"|"&D6&"|"&J6 -> КОМПО Технолоджис|План|Сервис|1 | S6: =A6&"|"&C6&"|"&D6&"|"&G6&"|"&J6 -> КОМПО Технолоджис|План|Сервис|2|1 | T6: =A6&"|"&C6&"|"&G6 -> КОМПО Технолоджис|План|2 | U6: =IF(H6="да",A6&"|"&C6&"|"&D6&"|"&J6,"") | V6: =IF(C6="План",A6&"|"&J6,"") -> КОМПО Технолоджис|1
A7: КОМПО Технолоджис | B7: РФ | C7: План | D7: Сервис | E7: План и бонусы | F7: Выручка 2025 | G7: 2 | J7: 2 | M7: 448343 | N7: EUR | O7: КТ | P7: E5 | Q7: =A7&"|"&C7&"|"&D7&"|"&G7 -> КОМПО Технолоджис|План|Сервис|2 | R7: =A7&"|"&C7&"|"&D7&"|"&J7 -> КОМПО Технолоджис|План|Сервис|2 | S7: =A7&"|"&C7&"|"&D7&"|"&G7&"|"&J7 -> КОМПО Технолоджис|План|Сервис|2|2 | T7: =A7&"|"&C7&"|"&G7 -> КОМПО Технолоджис|План|2 | U7: =IF(H7="да",A7&"|"&C7&"|"&D7&"|"&J7,"") | V7: =IF(C7="План",A7&"|"&J7,"") -> КОМПО Технолоджис|2
A8: КОМПО Технолоджис | B8: РФ | C8: План | D8: Сервис | E8: План и бонусы | F8: План 2026 | G8: 2 | J8: 3 | M8: 480438 | N8: EUR | O8: КТ | P8: F5 | Q8: =A8&"|"&C8&"|"&D8&"|"&G8 -> КОМПО Технолоджис|План|Сервис|2 | R8: =A8&"|"&C8&"|"&D8&"|"&J8 -> КОМПО Технолоджис|План|Сервис|3 | S8: =A8&"|"&C8&"|"&D8&"|"&G8&"|"&J8 -> КОМПО Технолоджис|План|Сервис|2|3 | T8: =A8&"|"&C8&"|"&G8 -> КОМПО Технолоджис|План|2 | U8: =IF(H8="да",A8&"|"&C8&"|"&D8&"|"&J8,"") | V8: =IF(C8="План",A8&"|"&J8,"") -> КОМПО Технолоджис|3
A9: КОМПО Технолоджис | B9: РФ | C9: План | D9: Сервис | E9: План и бонусы | F9: Размер бонуса по итогам 2026 г | G9: 2 | J9: 5 | M9: 0.01 | N9: % | O9: КТ | P9: H5 | Q9: =A9&"|"&C9&"|"&D9&"|"&G9 -> КОМПО Технолоджис|План|Сервис|2 | R9: =A9&"|"&C9&"|"&D9&"|"&J9 -> КОМПО Технолоджис|План|Сервис|5 | S9: =A9&"|"&C9&"|"&D9&"|"&G9&"|"&J9 -> КОМПО Технолоджис|План|Сервис|2|5 | T9: =A9&"|"&C9&"|"&G9 -> КОМПО Технолоджис|План|2 | U9: =IF(H9="да",A9&"|"&C9&"|"&D9&"|"&J9,"") | V9: =IF(C9="План",A9&"|"&J9,"") -> КОМПО Технолоджис|5
A10: КОМПО Технолоджис | B10: РФ | C10: План | D10: Сервис | E10: План и бонусы | F10: Скидка в 1 кв. 2026 ф.г.* | G10: 2 | J10: 6 | M10: 0.3 | N10: % | O10: КТ | P10: I5 | Q10: =A10&"|"&C10&"|"&D10&"|"&G10 -> КОМПО Технолоджис|План|Сервис|2 | R10: =A10&"|"&C10&"|"&D10&"|"&J10 -> КОМПО Технолоджис|План|Сервис|6 | S10: =A10&"|"&C10&"|"&D10&"|"&G10&"|"&J10 -> КОМПО Технолоджис|План|Сервис|2|6 | T10: =A10&"|"&C10&"|"&G10 -> КОМПО Технолоджис|План|2 | U10: =IF(H10="да",A10&"|"&C10&"|"&D10&"|"&J10,"") | V10: =IF(C10="План",A10&"|"&J10,"") -> КОМПО Технолоджис|6
A11: КОМПО Технолоджис | B11: РФ | C11: План | D11: Оборудование | E11: План и бонусы | F11: Выручка 2024 | G11: 3 | J11: 1 | M11: 2205660 | N11: EUR | O11: КТ | P11: D6 | Q11: =A11&"|"&C11&"|"&D11&"|"&G11 -> КОМПО Технолоджис|План|Оборудование|3 | R11: =A11&"|"&C11&"|"&D11&"|"&J11 -> КОМПО Технолоджис|План|Оборудование|1 | S11: =A11&"|"&C11&"|"&D11&"|"&G11&"|"&J11 -> КОМПО Технолоджис|План|Оборудование|3|1 | T11: =A11&"|"&C11&"|"&G11 -> КОМПО Технолоджис|План|3 | U11: =IF(H11="да",A11&"|"&C11&"|"&D11&"|"&J11,"") | V11: =IF(C11="План",A11&"|"&J11,"") -> КОМПО Технолоджис|1
A12: КОМПО Технолоджис | B12: РФ | C12: План | D12: Оборудование | E12: План и бонусы | F12: Выручка 2025 | G12: 3 | J12: 2 | M12: 1710368 | N12: EUR | O12: КТ | P12: E6 | Q12: =A12&"|"&C12&"|"&D12&"|"&G12 -> КОМПО Технолоджис|План|Оборудование|3 | R12: =A12&"|"&C12&"|"&D12&"|"&J12 -> КОМПО Технолоджис|План|Оборудование|2 | S12: =A12&"|"&C12&"|"&D12&"|"&G12&"|"&J12 -> КОМПО Технолоджис|План|Оборудование|3|2 | T12: =A12&"|"&C12&"|"&G12 -> КОМПО Технолоджис|План|3 | U12: =IF(H12="да",A12&"|"&C12&"|"&D12&"|"&J12,"") | V12: =IF(C12="План",A12&"|"&J12,"") -> КОМПО Технолоджис|2
A13: КОМПО Технолоджис | B13: РФ | C13: План | D13: Оборудование | E13: План и бонусы | F13: План 2026 | G13: 3 | J13: 3 | M13: 2020593.8 | N13: EUR | O13: КТ | P13: F6 | Q13: =A13&"|"&C13&"|"&D13&"|"&G13 -> КОМПО Технолоджис|План|Оборудование|3 | R13: =A13&"|"&C13&"|"&D13&"|"&J13 -> КОМПО Технолоджис|План|Оборудование|3 | S13: =A13&"|"&C13&"|"&D13&"|"&G13&"|"&J13 -> КОМПО Технолоджис|План|Оборудование|3|3 | T13: =A13&"|"&C13&"|"&G13 -> КОМПО Технолоджис|План|3 | U13: =IF(H13="да",A13&"|"&C13&"|"&D13&"|"&J13,"") | V13: =IF(C13="План",A13&"|"&J13,"") -> КОМПО Технолоджис|3
... A20: КОМПО Технолоджис | B20: РФ | C20: План | D20: Расходные материалы | E20: План и бонусы | F20: Скидка в 1 кв. 2026 ф.г.* | G20: 4 | J20: 6 | M20: 0.06 | N20: % | O20: КТ | P20: I7 | Q20: =A20&"|"&C20&"|"&D20&"|"&G20 -> КОМПО Технолоджис|План|Расходные материалы|4 | R20: =A20&"|"&C20&"|"&D20&"|"&J20 -> КОМПО Технолоджис|План|Расходные материалы|6 | S20: =A20&"|"&C20&"|"&D20&"|"&G20&"|"&J20 -> КОМПО Технолоджис|План|Расходные материалы|4|6 | T20: =A20&"|"&C20&"|"&G20 -> КОМПО Технолоджис|План|4 | U20: =IF(H20="да",A20&"|"&C20&"|"&D20&"|"&J20,"") | V20: =IF(C20="План",A20&"|"&J20,"") -> КОМПО Технолоджис|6
A21: КОМПО Технолоджис | B21: РФ | C21: Шкала | D21: Оборудование | E21: Оборудование — за квартал | F21: 1 Базовое вознаграждение за Дилерский договор | G21: 1 | I21: до 75 | J21: 1 | M21: 0.06 | N21: % | O21: КТ | P21: E13 | Q21: =A21&"|"&C21&"|"&D21&"|"&G21 -> КОМПО Технолоджис|Шкала|Оборудование|1 | R21: =A21&"|"&C21&"|"&D21&"|"&J21 -> КОМПО Технолоджис|Шкала|Оборудование|1 | S21: =A21&"|"&C21&"|"&D21&"|"&G21&"|"&J21 -> КОМПО Технолоджис|Шкала|Оборудование|1|1 | T21: =A21&"|"&C21&"|"&G21 -> КОМПО Технолоджис|Шкала|1 | U21: =IF(H21="да",A21&"|"&C21&"|"&D21&"|"&J21,"") | V21: =IF(C21="План",A21&"|"&J21,"")
A22: КОМПО Технолоджис | B22: РФ | C22: Шкала | D22: Оборудование | E22: Оборудование — за квартал | F22: 1 Базовое вознаграждение за Дилерский договор | G22: 1 | I22: 75-114 | J22: 2 | M22: 0.06 | N22: % | O22: КТ | P22: F13 | Q22: =A22&"|"&C22&"|"&D22&"|"&G22 -> КОМПО Технолоджис|Шкала|Оборудование|1 | R22: =A22&"|"&C22&"|"&D22&"|"&J22 -> КОМПО Технолоджис|Шкала|Оборудование|2 | S22: =A22&"|"&C22&"|"&D22&"|"&G22&"|"&J22 -> КОМПО Технолоджис|Шкала|Оборудование|1|2 | T22: =A22&"|"&C22&"|"&G22 -> КОМПО Технолоджис|Шкала|1 | U22: =IF(H22="да",A22&"|"&C22&"|"&D22&"|"&J22,"") | V22: =IF(C22="План",A22&"|"&J22,"")
A23: КОМПО Технолоджис | B23: РФ | C23: Шкала | D23: Оборудование | E23: Оборудование — за квартал | F23: 1 Базовое вознаграждение за Дилерский договор | G23: 1 | I23: 115-149 | J23: 3 | M23: 0.06 | N23: % | O23: КТ | P23: G13 | Q23: =A23&"|"&C23&"|"&D23&"|"&G23 -> КОМПО Технолоджис|Шкала|Оборудование|1 | R23: =A23&"|"&C23&"|"&D23&"|"&J23 -> КОМПО Технолоджис|Шкала|Оборудование|3 | S23: =A23&"|"&C23&"|"&D23&"|"&G23&"|"&J23 -> КОМПО Технолоджис|Шкала|Оборудование|1|3 | T23: =A23&"|"&C23&"|"&G23 -> КОМПО Технолоджис|Шкала|1 | U23: =IF(H23="да",A23&"|"&C23&"|"&D23&"|"&J23,"") | V23: =IF(C23="План",A23&"|"&J23,"")
A24: КОМПО Технолоджис | B24: РФ | C24: Шкала | D24: Оборудование | E24: Оборудование — за квартал | F24: 1 Базовое вознаграждение за Дилерский договор | G24: 1 | I24: 150-189 | J24: 4 | M24: 0.06 | N24: % | O24: КТ | P24: H13 | Q24: =A24&"|"&C24&"|"&D24&"|"&G24 -> КОМПО Технолоджис|Шкала|Оборудование|1 | R24: =A24&"|"&C24&"|"&D24&"|"&J24 -> КОМПО Технолоджис|Шкала|Оборудование|4 | S24: =A24&"|"&C24&"|"&D24&"|"&G24&"|"&J24 -> КОМПО Технолоджис|Шкала|Оборудование|1|4 | T24: =A24&"|"&C24&"|"&G24 -> КОМПО Технолоджис|Шкала|1 | U24: =IF(H24="да",A24&"|"&C24&"|"&D24&"|"&J24,"") | V24: =IF(C24="План",A24&"|"&J24,"")
A25: КОМПО Технолоджис | B25: РФ | C25: Шкала | D25: Оборудование | E25: Оборудование — за квартал | F25: 1 Базовое вознаграждение за Дилерский договор | G25: 1 | I25: 190-224 | J25: 5 | M25: 0.06 | N25: % | O25: КТ | P25: I13 | Q25: =A25&"|"&C25&"|"&D25&"|"&G25 -> КОМПО Технолоджис|Шкала|Оборудование|1 | R25: =A25&"|"&C25&"|"&D25&"|"&J25 -> КОМПО Технолоджис|Шкала|Оборудование|5 | S25: =A25&"|"&C25&"|"&D25&"|"&G25&"|"&J25 -> КОМПО Технолоджис|Шкала|Оборудование|1|5 | T25: =A25&"|"&C25&"|"&G25 -> КОМПО Технолоджис|Шкала|1 | U25: =IF(H25="да",A25&"|"&C25&"|"&D25&"|"&J25,"") | V25: =IF(C25="План",A25&"|"&J25,"")
A26: КОМПО Технолоджис | B26: РФ | C26: Шкала | D26: Оборудование | E26: Оборудование — за квартал | F26: 1 Базовое вознаграждение за Дилерский договор | G26: 1 | I26: 225 и более | J26: 6 | M26: 0.06 | N26: % | O26: КТ | P26: J13 | Q26: =A26&"|"&C26&"|"&D26&"|"&G26 -> КОМПО Технолоджис|Шкала|Оборудование|1 | R26: =A26&"|"&C26&"|"&D26&"|"&J26 -> КОМПО Технолоджис|Шкала|Оборудование|6 | S26: =A26&"|"&C26&"|"&D26&"|"&G26&"|"&J26 -> КОМПО Технолоджис|Шкала|Оборудование|1|6 | T26: =A26&"|"&C26&"|"&G26 -> КОМПО Технолоджис|Шкала|1 | U26: =IF(H26="да",A26&"|"&C26&"|"&D26&"|"&J26,"") | V26: =IF(C26="План",A26&"|"&J26,"")
A27: КОМПО Технолоджис | B27: РФ | C27: Шкала | D27: Оборудование | E27: Оборудование — за квартал | F27: 2.1.1. Сервисный центр | G27: 2 | I27: до 75 | J27: 1 | M27: 0.06 | N27: % | O27: КТ | P27: E14 | Q27: =A27&"|"&C27&"|"&D27&"|"&G27 -> КОМПО Технолоджис|Шкала|Оборудование|2 | R27: =A27&"|"&C27&"|"&D27&"|"&J27 -> КОМПО Технолоджис|Шкала|Оборудование|1 | S27: =A27&"|"&C27&"|"&D27&"|"&G27&"|"&J27 -> КОМПО Технолоджис|Шкала|Оборудование|2|1 | T27: =A27&"|"&C27&"|"&G27 -> КОМПО Технолоджис|Шкала|2 | U27: =IF(H27="да",A27&"|"&C27&"|"&D27&"|"&J27,"") | V27: =IF(C27="План",A27&"|"&J27,"")
A28: КОМПО Технолоджис | B28: РФ | C28: Шкала | D28: Оборудование | E28: Оборудование — за квартал | F28: 2.1.1. Сервисный центр | G28: 2 | I28: 75-114 | J28: 2 | M28: 0.06 | N28: % | O28: КТ | P28: F14 | Q28: =A28&"|"&C28&"|"&D28&"|"&G28 -> КОМПО Технолоджис|Шкала|Оборудование|2 | R28: =A28&"|"&C28&"|"&D28&"|"&J28 -> КОМПО Технолоджис|Шкала|Оборудование|2 | S28: =A28&"|"&C28&"|"&D28&"|"&G28&"|"&J28 -> КОМПО Технолоджис|Шкала|Оборудование|2|2 | T28: =A28&"|"&C28&"|"&G28 -> КОМПО Технолоджис|Шкала|2 | U28: =IF(H28="да",A28&"|"&C28&"|"&D28&"|"&J28,"") | V28: =IF(C28="План",A28&"|"&J28,"")
A29: КОМПО Технолоджис | B29: РФ | C29: Шкала | D29: Оборудование | E29: Оборудование — за квартал | F29: 2.1.1. Сервисный центр | G29: 2 | I29: 115-149 | J29: 3 | M29: 0.06 | N29: % | O29: КТ | P29: G14 | Q29: =A29&"|"&C29&"|"&D29&"|"&G29 -> КОМПО Технолоджис|Шкала|Оборудование|2 | R29: =A29&"|"&C29&"|"&D29&"|"&J29 -> КОМПО Технолоджис|Шкала|Оборудование|3 | S29: =A29&"|"&C29&"|"&D29&"|"&G29&"|"&J29 -> КОМПО Технолоджис|Шкала|Оборудование|2|3 | T29: =A29&"|"&C29&"|"&G29 -> КОМПО Технолоджис|Шкала|2 | U29: =IF(H29="да",A29&"|"&C29&"|"&D29&"|"&J29,"") | V29: =IF(C29="План",A29&"|"&J29,"")
A30: КОМПО Технолоджис | B30: РФ | C30: Шкала | D30: Оборудование | E30: Оборудование — за квартал | F30: 2.1.1. Сервисный центр | G30: 2 | I30: 150-189 | J30: 4 | M30: 0.06 | N30: % | O30: КТ | P30: H14 | Q30: =A30&"|"&C30&"|"&D30&"|"&G30 -> КОМПО Технолоджис|Шкала|Оборудование|2 | R30: =A30&"|"&C30&"|"&D30&"|"&J30 -> КОМПО Технолоджис|Шкала|Оборудование|4 | S30: =A30&"|"&C30&"|"&D30&"|"&G30&"|"&J30 -> КОМПО Технолоджис|Шкала|Оборудование|2|4 | T30: =A30&"|"&C30&"|"&G30 -> КОМПО Технолоджис|Шкала|2 | U30: =IF(H30="да",A30&"|"&C30&"|"&D30&"|"&J30,"") | V30: =IF(C30="План",A30&"|"&J30,"")
A31: КОМПО Технолоджис | B31: РФ | C31: Шкала | D31: Оборудование | E31: Оборудование — за квартал | F31: 2.1.1. Сервисный центр | G31: 2 | I31: 190-224 | J31: 5 | M31: 0.06 | N31: % | O31: КТ | P31: I14 | Q31: =A31&"|"&C31&"|"&D31&"|"&G31 -> КОМПО Технолоджис|Шкала|Оборудование|2 | R31: =A31&"|"&C31&"|"&D31&"|"&J31 -> КОМПО Технолоджис|Шкала|Оборудование|5 | S31: =A31&"|"&C31&"|"&D31&"|"&G31&"|"&J31 -> КОМПО Технолоджис|Шкала|Оборудование|2|5 | T31: =A31&"|"&C31&"|"&G31 -> КОМПО Технолоджис|Шкала|2 | U31: =IF(H31="да",A31&"|"&C31&"|"&D31&"|"&J31,"") | V31: =IF(C31="План",A31&"|"&J31,"")
A32: КОМПО Технолоджис | B32: РФ | C32: Шкала | D32: Оборудование | E32: Оборудование — за квартал | F32: 2.1.1. Сервисный центр | G32: 2 | I32: 225 и более | J32: 6 | M32: 0.06 | N32: % | O32: КТ | P32: J14 | Q32: =A32&"|"&C32&"|"&D32&"|"&G32 -> КОМПО Технолоджис|Шкала|Оборудование|2 | R32: =A32&"|"&C32&"|"&D32&"|"&J32 -> КОМПО Технолоджис|Шкала|Оборудование|6 | S32: =A32&"|"&C32&"|"&D32&"|"&G32&"|"&J32 -> КОМПО Технолоджис|Шкала|Оборудование|2|6 | T32: =A32&"|"&C32&"|"&G32 -> КОМПО Технолоджис|Шкала|2 | U32: =IF(H32="да",A32&"|"&C32&"|"&D32&"|"&J32,"") | V32: =IF(C32="План",A32&"|"&J32,"")
... A50: КОМПО Технолоджис | B50: РФ | C50: Шкала | D50: Оборудование | E50: Оборудование — за квартал | F50: 3 Объем закупок МП | G50: 5 | I50: 225 и более | J50: 6 | M50: 0.05 | N50: % | O50: КТ | P50: J17 | Q50: =A50&"|"&C50&"|"&D50&"|"&G50 -> КОМПО Технолоджис|Шкала|Оборудование|5 | R50: =A50&"|"&C50&"|"&D50&"|"&J50 -> КОМПО Технолоджис|Шкала|Оборудование|6 | S50: =A50&"|"&C50&"|"&D50&"|"&G50&"|"&J50 -> КОМПО Технолоджис|Шкала|Оборудование|5|6 | T50: =A50&"|"&C50&"|"&G50 -> КОМПО Технолоджис|Шкала|5 | U50: =IF(H50="да",A50&"|"&C50&"|"&D50&"|"&J50,"") | V50: =IF(C50="План",A50&"|"&J50,"")
A51: КОМПО Технолоджис | B51: РФ | C51: Шкала | D51: Оборудование | E51: Оборудование — за квартал | F51: ИТОГО по МП: | G51: 6 | H51: да | I51: до 75 | J51: 1 | M51: 0.14 | N51: % | O51: КТ | P51: E18 | Q51: =A51&"|"&C51&"|"&D51&"|"&G51 -> КОМПО Технолоджис|Шкала|Оборудование|6 | R51: =A51&"|"&C51&"|"&D51&"|"&J51 -> КОМПО Технолоджис|Шкала|Оборудование|1 | S51: =A51&"|"&C51&"|"&D51&"|"&G51&"|"&J51 -> КОМПО Технолоджис|Шкала|Оборудование|6|1 | T51: =A51&"|"&C51&"|"&G51 -> КОМПО Технолоджис|Шкала|6 | U51: =IF(H51="да",A51&"|"&C51&"|"&D51&"|"&J51,"") -> КОМПО Технолоджис|Шкала|Оборудование|1 | V51: =IF(C51="План",A51&"|"&J51,"")
A52: КОМПО Технолоджис | B52: РФ | C52: Шкала | D52: Оборудование | E52: Оборудование — за квартал | F52: ИТОГО по МП: | G52: 6 | H52: да | I52: 75-114 | J52: 2 | M52: 0.15 | N52: % | O52: КТ | P52: F18 | Q52: =A52&"|"&C52&"|"&D52&"|"&G52 -> КОМПО Технолоджис|Шкала|Оборудование|6 | R52: =A52&"|"&C52&"|"&D52&"|"&J52 -> КОМПО Технолоджис|Шкала|Оборудование|2 | S52: =A52&"|"&C52&"|"&D52&"|"&G52&"|"&J52 -> КОМПО Технолоджис|Шкала|Оборудование|6|2 | T52: =A52&"|"&C52&"|"&G52 -> КОМПО Технолоджис|Шкала|6 | U52: =IF(H52="да",A52&"|"&C52&"|"&D52&"|"&J52,"") -> КОМПО Технолоджис|Шкала|Оборудование|2 | V52: =IF(C52="План",A52&"|"&J52,"")
A53: КОМПО Технолоджис | B53: РФ | C53: Шкала | D53: Оборудование | E53: Оборудование — за квартал | F53: ИТОГО по МП: | G53: 6 | H53: да | I53: 115-149 | J53: 3 | M53: 0.16 | N53: % | O53: КТ | P53: G18 | Q53: =A53&"|"&C53&"|"&D53&"|"&G53 -> КОМПО Технолоджис|Шкала|Оборудование|6 | R53: =A53&"|"&C53&"|"&D53&"|"&J53 -> КОМПО Технолоджис|Шкала|Оборудование|3 | S53: =A53&"|"&C53&"|"&D53&"|"&G53&"|"&J53 -> КОМПО Технолоджис|Шкала|Оборудование|6|3 | T53: =A53&"|"&C53&"|"&G53 -> КОМПО Технолоджис|Шкала|6 | U53: =IF(H53="да",A53&"|"&C53&"|"&D53&"|"&J53,"") -> КОМПО Технолоджис|Шкала|Оборудование|3 | V53: =IF(C53="План",A53&"|"&J53,"")
A54: КОМПО Технолоджис | B54: РФ | C54: Шкала | D54: Оборудование | E54: Оборудование — за квартал | F54: ИТОГО по МП: | G54: 6 | H54: да | I54: 150-189 | J54: 4 | M54: 0.17 | N54: % | O54: КТ | P54: H18 | Q54: =A54&"|"&C54&"|"&D54&"|"&G54 -> КОМПО Технолоджис|Шкала|Оборудование|6 | R54: =A54&"|"&C54&"|"&D54&"|"&J54 -> КОМПО Технолоджис|Шкала|Оборудование|4 | S54: =A54&"|"&C54&"|"&D54&"|"&G54&"|"&J54 -> КОМПО Технолоджис|Шкала|Оборудование|6|4 | T54: =A54&"|"&C54&"|"&G54 -> КОМПО Технолоджис|Шкала|6 | U54: =IF(H54="да",A54&"|"&C54&"|"&D54&"|"&J54,"") -> КОМПО Технолоджис|Шкала|Оборудование|4 | V54: =IF(C54="План",A54&"|"&J54,"")
A55: КОМПО Технолоджис | B55: РФ | C55: Шкала | D55: Оборудование | E55: Оборудование — за квартал | F55: ИТОГО по МП: | G55: 6 | H55: да | I55: 190-224 | J55: 5 | M55: 0.18 | N55: % | O55: КТ | P55: I18 | Q55: =A55&"|"&C55&"|"&D55&"|"&G55 -> КОМПО Технолоджис|Шкала|Оборудование|6 | R55: =A55&"|"&C55&"|"&D55&"|"&J55 -> КОМПО Технолоджис|Шкала|Оборудование|5 | S55: =A55&"|"&C55&"|"&D55&"|"&G55&"|"&J55 -> КОМПО Технолоджис|Шкала|Оборудование|6|5 | T55: =A55&"|"&C55&"|"&G55 -> КОМПО Технолоджис|Шкала|6 | U55: =IF(H55="да",A55&"|"&C55&"|"&D55&"|"&J55,"") -> КОМПО Технолоджис|Шкала|Оборудование|5 | V55: =IF(C55="План",A55&"|"&J55,"")
A56: КОМПО Технолоджис | B56: РФ | C56: Шкала | D56: Оборудование | E56: Оборудование — за квартал | F56: ИТОГО по МП: | G56: 6 | H56: да | I56: 225 и более | J56: 6 | M56: 0.19 | N56: % | O56: КТ | P56: J18 | Q56: =A56&"|"&C56&"|"&D56&"|"&G56 -> КОМПО Технолоджис|Шкала|Оборудование|6 | R56: =A56&"|"&C56&"|"&D56&"|"&J56 -> КОМПО Технолоджис|Шкала|Оборудование|6 | S56: =A56&"|"&C56&"|"&D56&"|"&G56&"|"&J56 -> КОМПО Технолоджис|Шкала|Оборудование|6|6 | T56: =A56&"|"&C56&"|"&G56 -> КОМПО Технолоджис|Шкала|6 | U56: =IF(H56="да",A56&"|"&C56&"|"&D56&"|"&J56,"") -> КОМПО Технолоджис|Шкала|Оборудование|6 | V56: =IF(C56="План",A56&"|"&J56,"")
A57: КОМПО Технолоджис | B57: РФ | C57: Шкала | D57: Оборудование | E57: Оборудование — за квартал | F57: Наличие минимальных складских остатков по РМ (синхронизация отчета по остаткам с 1С КОМПО) | G57: 7 | I57: до 75 | J57: 1 | M57: 0.01 | N57: % | O57: КТ | P57: E20 | Q57: =A57&"|"&C57&"|"&D57&"|"&G57 -> КОМПО Технолоджис|Шкала|Оборудование|7 | R57: =A57&"|"&C57&"|"&D57&"|"&J57 -> КОМПО Технолоджис|Шкала|Оборудование|1 | S57: =A57&"|"&C57&"|"&D57&"|"&G57&"|"&J57 -> КОМПО Технолоджис|Шкала|Оборудование|7|1 | T57: =A57&"|"&C57&"|"&G57 -> КОМПО Технолоджис|Шкала|7 | U57: =IF(H57="да",A57&"|"&C57&"|"&D57&"|"&J57,"") | V57: =IF(C57="План",A57&"|"&J57,"")
A58: КОМПО Технолоджис | B58: РФ | C58: Шкала | D58: Оборудование | E58: Оборудование — за квартал | F58: Наличие минимальных складских остатков по РМ (синхронизация отчета по остаткам с 1С КОМПО) | G58: 7 | I58: 75-114 | J58: 2 | M58: 0.01 | N58: % | O58: КТ | P58: F20 | Q58: =A58&"|"&C58&"|"&D58&"|"&G58 -> КОМПО Технолоджис|Шкала|Оборудование|7 | R58: =A58&"|"&C58&"|"&D58&"|"&J58 -> КОМПО Технолоджис|Шкала|Оборудование|2 | S58: =A58&"|"&C58&"|"&D58&"|"&G58&"|"&J58 -> КОМПО Технолоджис|Шкала|Оборудование|7|2 | T58: =A58&"|"&C58&"|"&G58 -> КОМПО Технолоджис|Шкала|7 | U58: =IF(H58="да",A58&"|"&C58&"|"&D58&"|"&J58,"") | V58: =IF(C58="План",A58&"|"&J58,"")
A59: КОМПО Технолоджис | B59: РФ | C59: Шкала | D59: Оборудование | E59: Оборудование — за квартал | F59: Наличие минимальных складских остатков по РМ (синхронизация отчета по остаткам с 1С КОМПО) | G59: 7 | I59: 115-149 | J59: 3 | M59: 0.01 | N59: % | O59: КТ | P59: G20 | Q59: =A59&"|"&C59&"|"&D59&"|"&G59 -> КОМПО Технолоджис|Шкала|Оборудование|7 | R59: =A59&"|"&C59&"|"&D59&"|"&J59 -> КОМПО Технолоджис|Шкала|Оборудование|3 | S59: =A59&"|"&C59&"|"&D59&"|"&G59&"|"&J59 -> КОМПО Технолоджис|Шкала|Оборудование|7|3 | T59: =A59&"|"&C59&"|"&G59 -> КОМПО Технолоджис|Шкала|7 | U59: =IF(H59="да",A59&"|"&C59&"|"&D59&"|"&J59,"") | V59: =IF(C59="План",A59&"|"&J59,"")
A60: КОМПО Технолоджис | B60: РФ | C60: Шкала | D60: Оборудование | E60: Оборудование — за квартал | F60: Наличие минимальных складских остатков по РМ (синхронизация отчета по остаткам с 1С КОМПО) | G60: 7 | I60: 150-189 | J60: 4 | M60: 0.01 | N60: % | O60: КТ | P60: H20 | Q60: =A60&"|"&C60&"|"&D60&"|"&G60 -> КОМПО Технолоджис|Шкала|Оборудование|7 | R60: =A60&"|"&C60&"|"&D60&"|"&J60 -> КОМПО Технолоджис|Шкала|Оборудование|4 | S60: =A60&"|"&C60&"|"&D60&"|"&G60&"|"&J60 -> КОМПО Технолоджис|Шкала|Оборудование|7|4 | T60: =A60&"|"&C60&"|"&G60 -> КОМПО Технолоджис|Шкала|7 | U60: =IF(H60="да",A60&"|"&C60&"|"&D60&"|"&J60,"") | V60: =IF(C60="План",A60&"|"&J60,"")
A61: КОМПО Технолоджис | B61: РФ | C61: Шкала | D61: Оборудование | E61: Оборудование — за квартал | F61: Наличие минимальных складских остатков по РМ (синхронизация отчета по остаткам с 1С КОМПО) | G61: 7 | I61: 190-224 | J61: 5 | M61: 0.01 | N61: % | O61: КТ | P61: I20 | Q61: =A61&"|"&C61&"|"&D61&"|"&G61 -> КОМПО Технолоджис|Шкала|Оборудование|7 | R61: =A61&"|"&C61&"|"&D61&"|"&J61 -> КОМПО Технолоджис|Шкала|Оборудование|5 | S61: =A61&"|"&C61&"|"&D61&"|"&G61&"|"&J61 -> КОМПО Технолоджис|Шкала|Оборудование|7|5 | T61: =A61&"|"&C61&"|"&G61 -> КОМПО Технолоджис|Шкала|7 | U61: =IF(H61="да",A61&"|"&C61&"|"&D61&"|"&J61,"") | V61: =IF(C61="План",A61&"|"&J61,"")
A62: КОМПО Технолоджис | B62: РФ | C62: Шкала | D62: Оборудование | E62: Оборудование — за квартал | F62: Наличие минимальных складских остатков по РМ (синхронизация отчета по остаткам с 1С КОМПО) | G62: 7 | I62: 225 и более | J62: 6 | M62: 0.01 | N62: % | O62: КТ | P62: J20 | Q62: =A62&"|"&C62&"|"&D62&"|"&G62 -> КОМПО Технолоджис|Шкала|Оборудование|7 | R62: =A62&"|"&C62&"|"&D62&"|"&J62 -> КОМПО Технолоджис|Шкала|Оборудование|6 | S62: =A62&"|"&C62&"|"&D62&"|"&G62&"|"&J62 -> КОМПО Технолоджис|Шкала|Оборудование|7|6 | T62: =A62&"|"&C62&"|"&G62 -> КОМПО Технолоджис|Шкала|7 | U62: =IF(H62="да",A62&"|"&C62&"|"&D62&"|"&J62,"") | V62: =IF(C62="План",A62&"|"&J62,"")
A63: КОМПО Технолоджис | B63: РФ | C63: Шкала | D63: Оборудование | E63: Оборудование — за квартал | F63: Объем закупок РМ | G63: 8 | I63: до 75 | J63: 1 | M63: 0 | N63: % | O63: КТ | P63: E21 | Q63: =A63&"|"&C63&"|"&D63&"|"&G63 -> КОМПО Технолоджис|Шкала|Оборудование|8 | R63: =A63&"|"&C63&"|"&D63&"|"&J63 -> КОМПО Технолоджис|Шкала|Оборудование|1 | S63: =A63&"|"&C63&"|"&D63&"|"&G63&"|"&J63 -> КОМПО Технолоджис|Шкала|Оборудование|8|1 | T63: =A63&"|"&C63&"|"&G63 -> КОМПО Технолоджис|Шкала|8 | U63: =IF(H63="да",A63&"|"&C63&"|"&D63&"|"&J63,"") | V63: =IF(C63="План",A63&"|"&J63,"")
A64: КОМПО Технолоджис | B64: РФ | C64: Шкала | D64: Оборудование | E64: Оборудование — за квартал | F64: Объем закупок РМ | G64: 8 | I64: 75-114 | J64: 2 | M64: 0.01 | N64: % | O64: КТ | P64: F21 | Q64: =A64&"|"&C64&"|"&D64&"|"&G64 -> КОМПО Технолоджис|Шкала|Оборудование|8 | R64: =A64&"|"&C64&"|"&D64&"|"&J64 -> КОМПО Технолоджис|Шкала|Оборудование|2 | S64: =A64&"|"&C64&"|"&D64&"|"&G64&"|"&J64 -> КОМПО Технолоджис|Шкала|Оборудование|8|2 | T64: =A64&"|"&C64&"|"&G64 -> КОМПО Технолоджис|Шкала|8 | U64: =IF(H64="да",A64&"|"&C64&"|"&D64&"|"&J64,"") | V64: =IF(C64="План",A64&"|"&J64,"")
A65: КОМПО Технолоджис | B65: РФ | C65: Шкала | D65: Оборудование | E65: Оборудование — за квартал | F65: Объем закупок РМ | G65: 8 | I65: 115-149 | J65: 3 | M65: 0.02 | N65: % | O65: КТ | P65: G21 | Q65: =A65&"|"&C65&"|"&D65&"|"&G65 -> КОМПО Технолоджис|Шкала|Оборудование|8 | R65: =A65&"|"&C65&"|"&D65&"|"&J65 -> КОМПО Технолоджис|Шкала|Оборудование|3 | S65: =A65&"|"&C65&"|"&D65&"|"&G65&"|"&J65 -> КОМПО Технолоджис|Шкала|Оборудование|8|3 | T65: =A65&"|"&C65&"|"&G65 -> КОМПО Технолоджис|Шкала|8 | U65: =IF(H65="да",A65&"|"&C65&"|"&D65&"|"&J65,"") | V65: =IF(C65="План",A65&"|"&J65,"")
A66: КОМПО Технолоджис | B66: РФ | C66: Шкала | D66: Оборудование | E66: Оборудование — за квартал | F66: Объем закупок РМ | G66: 8 | I66: 150-189 | J66: 4 | M66: 0.03 | N66: % | O66: КТ | P66: H21 | Q66: =A66&"|"&C66&"|"&D66&"|"&G66 -> КОМПО Технолоджис|Шкала|Оборудование|8 | R66: =A66&"|"&C66&"|"&D66&"|"&J66 -> КОМПО Технолоджис|Шкала|Оборудование|4 | S66: =A66&"|"&C66&"|"&D66&"|"&G66&"|"&J66 -> КОМПО Технолоджис|Шкала|Оборудование|8|4 | T66: =A66&"|"&C66&"|"&G66 -> КОМПО Технолоджис|Шкала|8 | U66: =IF(H66="да",A66&"|"&C66&"|"&D66&"|"&J66,"") | V66: =IF(C66="План",A66&"|"&J66,"")
A67: КОМПО Технолоджис | B67: РФ | C67: Шкала | D67: Оборудование | E67: Оборудование — за квартал | F67: Объем закупок РМ | G67: 8 | I67: 190-224 | J67: 5 | M67: 0.04 | N67: % | O67: КТ | P67: I21 | Q67: =A67&"|"&C67&"|"&D67&"|"&G67 -> КОМПО Технолоджис|Шкала|Оборудование|8 | R67: =A67&"|"&C67&"|"&D67&"|"&J67 -> КОМПО Технолоджис|Шкала|Оборудование|5 | S67: =A67&"|"&C67&"|"&D67&"|"&G67&"|"&J67 -> КОМПО Технолоджис|Шкала|Оборудование|8|5 | T67: =A67&"|"&C67&"|"&G67 -> КОМПО Технолоджис|Шкала|8 | U67: =IF(H67="да",A67&"|"&C67&"|"&D67&"|"&J67,"") | V67: =IF(C67="План",A67&"|"&J67,"")
A68: КОМПО Технолоджис | B68: РФ | C68: Шкала | D68: Оборудование | E68: Оборудование — за квартал | F68: Объем закупок РМ | G68: 8 | I68: 225 и более | J68: 6 | M68: 0.05 | N68: % | O68: КТ | P68: J21 | Q68: =A68&"|"&C68&"|"&D68&"|"&G68 -> КОМПО Технолоджис|Шкала|Оборудование|8 | R68: =A68&"|"&C68&"|"&D68&"|"&J68 -> КОМПО Технолоджис|Шкала|Оборудование|6 | S68: =A68&"|"&C68&"|"&D68&"|"&G68&"|"&J68 -> КОМПО Технолоджис|Шкала|Оборудование|8|6 | T68: =A68&"|"&C68&"|"&G68 -> КОМПО Технолоджис|Шкала|8 | U68: =IF(H68="да",A68&"|"&C68&"|"&D68&"|"&J68,"") | V68: =IF(C68="План",A68&"|"&J68,"")
... A80: КОМПО Технолоджис | B80: РФ | C80: Шкала | D80: Расходные материалы | E80: Расходные материалы — за квартал | F80: Объем закупок РМ | G80: 2 | I80: 225 и более | J80: 6 | M80: 0.05 | N80: % | O80: КТ | P80: J21 | Q80: =A80&"|"&C80&"|"&D80&"|"&G80 -> КОМПО Технолоджис|Шкала|Расходные материалы|2 | R80: =A80&"|"&C80&"|"&D80&"|"&J80 -> КОМПО Технолоджис|Шкала|Расходные материалы|6 | S80: =A80&"|"&C80&"|"&D80&"|"&G80&"|"&J80 -> КОМПО Технолоджис|Шкала|Расходные материалы|2|6 | T80: =A80&"|"&C80&"|"&G80 -> КОМПО Технолоджис|Шкала|2 | U80: =IF(H80="да",A80&"|"&C80&"|"&D80&"|"&J80,"") | V80: =IF(C80="План",A80&"|"&J80,"")
A81: КОМПО Технолоджис | B81: РФ | C81: Шкала | D81: Сервис (ЗЧ) | E81: Сервис (ЗЧ) — расчёт по парку оборудования | F81: Скидка по сервису | G81: 1 | H81: да | I81: 0–500 | J81: 1 | K81: 0 | L81: 500 | M81: 0.19 | N81: % | O81: КТ | P81: F26 | Q81: =A81&"|"&C81&"|"&D81&"|"&G81 -> КОМПО Технолоджис|Шкала|Сервис (ЗЧ)|1 | R81: =A81&"|"&C81&"|"&D81&"|"&J81 -> КОМПО Технолоджис|Шкала|Сервис (ЗЧ)|1 | S81: =A81&"|"&C81&"|"&D81&"|"&G81&"|"&J81 -> КОМПО Технолоджис|Шкала|Сервис (ЗЧ)|1|1 | T81: =A81&"|"&C81&"|"&G81 -> КОМПО Технолоджис|Шкала|1 | U81: =IF(H81="да",A81&"|"&C81&"|"&D81&"|"&J81,"") -> КОМПО Технолоджис|Шкала|Сервис (ЗЧ)|1 | V81: =IF(C81="План",A81&"|"&J81,"")
A82: КОМПО Технолоджис | B82: РФ | C82: Шкала | D82: Сервис (ЗЧ) | E82: Сервис (ЗЧ) — расчёт по парку оборудования | F82: Скидка по сервису | G82: 1 | H82: да | I82: 501–1000 | J82: 2 | K82: 501 | L82: 1000 | M82: 0.21 | N82: % | O82: КТ | P82: F27 | Q82: =A82&"|"&C82&"|"&D82&"|"&G82 -> КОМПО Технолоджис|Шкала|Сервис (ЗЧ)|1 | R82: =A82&"|"&C82&"|"&D82&"|"&J82 -> КОМПО Технолоджис|Шкала|Сервис (ЗЧ)|2 | S82: =A82&"|"&C82&"|"&D82&"|"&G82&"|"&J82 -> КОМПО Технолоджис|Шкала|Сервис (ЗЧ)|1|2 | T82: =A82&"|"&C82&"|"&G82 -> КОМПО Технолоджис|Шкала|1 | U82: =IF(H82="да",A82&"|"&C82&"|"&D82&"|"&J82,"") -> КОМПО Технолоджис|Шкала|Сервис (ЗЧ)|2 | V82: =IF(C82="План",A82&"|"&J82,"")
A83: КОМПО Технолоджис | B83: РФ | C83: Шкала | D83: Сервис (ЗЧ) | E83: Сервис (ЗЧ) — расчёт по парку оборудования | F83: Скидка по сервису | G83: 1 | H83: да | I83: 1001–1800 | J83: 3 | K83: 1001 | L83: 1800 | M83: 0.23 | N83: % | O83: КТ | P83: F28 | Q83: =A83&"|"&C83&"|"&D83&"|"&G83 -> КОМПО Технолоджис|Шкала|Сервис (ЗЧ)|1 | R83: =A83&"|"&C83&"|"&D83&"|"&J83 -> КОМПО Технолоджис|Шкала|Сервис (ЗЧ)|3 | S83: =A83&"|"&C83&"|"&D83&"|"&G83&"|"&J83 -> КОМПО Технолоджис|Шкала|Сервис (ЗЧ)|1|3 | T83: =A83&"|"&C83&"|"&G83 -> КОМПО Технолоджис|Шкала|1 | U83: =IF(H83="да",A83&"|"&C83&"|"&D83&"|"&J83,"") -> КОМПО Технолоджис|Шкала|Сервис (ЗЧ)|3 | V83: =IF(C83="План",A83&"|"&J83,"")
A84: КОМПО Технолоджис | B84: РФ | C84: Шкала | D84: Сервис (ЗЧ) | E84: Сервис (ЗЧ) — расчёт по парку оборудования | F84: Скидка по сервису | G84: 1 | H84: да | I84: 1801–2400 | J84: 4 | K84: 1801 | L84: 2400 | M84: 0.25 | N84: % | O84: КТ | P84: F29 | Q84: =A84&"|"&C84&"|"&D84&"|"&G84 -> КОМПО Технолоджис|Шкала|Сервис (ЗЧ)|1 | R84: =A84&"|"&C84&"|"&D84&"|"&J84 -> КОМПО Технолоджис|Шкала|Сервис (ЗЧ)|4 | S84: =A84&"|"&C84&"|"&D84&"|"&G84&"|"&J84 -> КОМПО Технолоджис|Шкала|Сервис (ЗЧ)|1|4 | T84: =A84&"|"&C84&"|"&G84 -> КОМПО Технолоджис|Шкала|1 | U84: =IF(H84="да",A84&"|"&C84&"|"&D84&"|"&J84,"") -> КОМПО Технолоджис|Шкала|Сервис (ЗЧ)|4 | V84: =IF(C84="План",A84&"|"&J84,"")
A85: КОМПО Технолоджис | B85: РФ | C85: Шкала | D85: Сервис (ЗЧ) | E85: Сервис (ЗЧ) — расчёт по парку оборудования | F85: Скидка по сервису | G85: 1 | H85: да | I85: 2401–3000 | J85: 5 | K85: 2401 | L85: 3000 | M85: 0.27 | N85: % | O85: КТ | P85: F30 | Q85: =A85&"|"&C85&"|"&D85&"|"&G85 -> КОМПО Технолоджис|Шкала|Сервис (ЗЧ)|1 | R85: =A85&"|"&C85&"|"&D85&"|"&J85 -> КОМПО Технолоджис|Шкала|Сервис (ЗЧ)|5 | S85: =A85&"|"&C85&"|"&D85&"|"&G85&"|"&J85 -> КОМПО Технолоджис|Шкала|Сервис (ЗЧ)|1|5 | T85: =A85&"|"&C85&"|"&G85 -> КОМПО Технолоджис|Шкала|1 | U85: =IF(H85="да",A85&"|"&C85&"|"&D85&"|"&J85,"") -> КОМПО Технолоджис|Шкала|Сервис (ЗЧ)|5 | V85: =IF(C85="План",A85&"|"&J85,"")
A86: КОМПО Технолоджис | B86: РФ | C86: Шкала | D86: Сервис (ЗЧ) | E86: Сервис (ЗЧ) — расчёт по парку оборудования | F86: Скидка по сервису | G86: 1 | H86: да | I86: 3001+ | J86: 6 | K86: 3001 | M86: 0.3 | N86: % | O86: КТ | P86: F31 | Q86: =A86&"|"&C86&"|"&D86&"|"&G86 -> КОМПО Технолоджис|Шкала|Сервис (ЗЧ)|1 | R86: =A86&"|"&C86&"|"&D86&"|"&J86 -> КОМПО Технолоджис|Шкала|Сервис (ЗЧ)|6 | S86: =A86&"|"&C86&"|"&D86&"|"&G86&"|"&J86 -> КОМПО Технолоджис|Шкала|Сервис (ЗЧ)|1|6 | T86: =A86&"|"&C86&"|"&G86 -> КОМПО Технолоджис|Шкала|1 | U86: =IF(H86="да",A86&"|"&C86&"|"&D86&"|"&J86,"") -> КОМПО Технолоджис|Шкала|Сервис (ЗЧ)|6 | V86: =IF(C86="План",A86&"|"&J86,"")
A87: НоваПак | B87: РФ | C87: План | D87: Итого по дилеру | E87: План и бонусы | F87: Выручка 2024 | G87: 1 | J87: 1 | M87: 1609061 | N87: EUR | O87: НоваПак | P87: D4 | Q87: =A87&"|"&C87&"|"&D87&"|"&G87 -> НоваПак|План|Итого по дилеру|1 | R87: =A87&"|"&C87&"|"&D87&"|"&J87 -> НоваПак|План|Итого по дилеру|1 | S87: =A87&"|"&C87&"|"&D87&"|"&G87&"|"&J87 -> НоваПак|План|Итого по дилеру|1|1 | T87: =A87&"|"&C87&"|"&G87 -> НоваПак|План|1 | U87: =IF(H87="да",A87&"|"&C87&"|"&D87&"|"&J87,"") | V87: =IF(C87="План",A87&"|"&J87,"") -> НоваПак|1
A88: НоваПак | B88: РФ | C88: План | D88: Итого по дилеру | E88: План и бонусы | F88: Выручка 2025 | G88: 1 | J88: 2 | M88: 1299534 | N88: EUR | O88: НоваПак | P88: E4 | Q88: =A88&"|"&C88&"|"&D88&"|"&G88 -> НоваПак|План|Итого по дилеру|1 | R88: =A88&"|"&C88&"|"&D88&"|"&J88 -> НоваПак|План|Итого по дилеру|2 | S88: =A88&"|"&C88&"|"&D88&"|"&G88&"|"&J88 -> НоваПак|План|Итого по дилеру|1|2 | T88: =A88&"|"&C88&"|"&G88 -> НоваПак|План|1 | U88: =IF(H88="да",A88&"|"&C88&"|"&D88&"|"&J88,"") | V88: =IF(C88="План",A88&"|"&J88,"") -> НоваПак|2
A89: НоваПак | B89: РФ | C89: План | D89: Итого по дилеру | E89: План и бонусы | F89: План 2026 | G89: 1 | J89: 3 | M89: 1812000 | N89: EUR | O89: НоваПак | P89: F4 | Q89: =A89&"|"&C89&"|"&D89&"|"&G89 -> НоваПак|План|Итого по дилеру|1 | R89: =A89&"|"&C89&"|"&D89&"|"&J89 -> НоваПак|План|Итого по дилеру|3 | S89: =A89&"|"&C89&"|"&D89&"|"&G89&"|"&J89 -> НоваПак|План|Итого по дилеру|1|3 | T89: =A89&"|"&C89&"|"&G89 -> НоваПак|План|1 | U89: =IF(H89="да",A89&"|"&C89&"|"&D89&"|"&J89,"") | V89: =IF(C89="План",A89&"|"&J89,"") -> НоваПак|3
A90: НоваПак | B90: РФ | C90: План | D90: Итого по дилеру | E90: План и бонусы | F90: Прирост П/Ф | G90: 1 | J90: 4 | M90: 0.39434597 | N90: % | O90: НоваПак | P90: G4 | Q90: =A90&"|"&C90&"|"&D90&"|"&G90 -> НоваПак|План|Итого по дилеру|1 | R90: =A90&"|"&C90&"|"&D90&"|"&J90 -> НоваПак|План|Итого по дилеру|4 | S90: =A90&"|"&C90&"|"&D90&"|"&G90&"|"&J90 -> НоваПак|План|Итого по дилеру|1|4 | T90: =A90&"|"&C90&"|"&G90 -> НоваПак|План|1 | U90: =IF(H90="да",A90&"|"&C90&"|"&D90&"|"&J90,"") | V90: =IF(C90="План",A90&"|"&J90,"") -> НоваПак|4
A91: НоваПак | B91: РФ | C91: План | D91: Сервис | E91: План и бонусы | F91: Выручка 2024 | G91: 2 | J91: 1 | M91: 233434 | N91: EUR | O91: НоваПак | P91: D5 | Q91: =A91&"|"&C91&"|"&D91&"|"&G91 -> НоваПак|План|Сервис|2 | R91: =A91&"|"&C91&"|"&D91&"|"&J91 -> НоваПак|План|Сервис|1 | S91: =A91&"|"&C91&"|"&D91&"|"&G91&"|"&J91 -> НоваПак|План|Сервис|2|1 | T91: =A91&"|"&C91&"|"&G91 -> НоваПак|План|2 | U91: =IF(H91="да",A91&"|"&C91&"|"&D91&"|"&J91,"") | V91: =IF(C91="План",A91&"|"&J91,"") -> НоваПак|1
A92: НоваПак | B92: РФ | C92: План | D92: Сервис | E92: План и бонусы | F92: Выручка 2025 | G92: 2 | J92: 2 | M92: 302280 | N92: EUR | O92: НоваПак | P92: E5 | Q92: =A92&"|"&C92&"|"&D92&"|"&G92 -> НоваПак|План|Сервис|2 | R92: =A92&"|"&C92&"|"&D92&"|"&J92 -> НоваПак|План|Сервис|2 | S92: =A92&"|"&C92&"|"&D92&"|"&G92&"|"&J92 -> НоваПак|План|Сервис|2|2 | T92: =A92&"|"&C92&"|"&G92 -> НоваПак|План|2 | U92: =IF(H92="да",A92&"|"&C92&"|"&D92&"|"&J92,"") | V92: =IF(C92="План",A92&"|"&J92,"") -> НоваПак|2
A93: НоваПак | B93: РФ | C93: План | D93: Сервис | E93: План и бонусы | F93: План 2026 | G93: 2 | J93: 3 | M93: 365000 | N93: EUR | O93: НоваПак | P93: F5 | Q93: =A93&"|"&C93&"|"&D93&"|"&G93 -> НоваПак|План|Сервис|2 | R93: =A93&"|"&C93&"|"&D93&"|"&J93 -> НоваПак|План|Сервис|3 | S93: =A93&"|"&C93&"|"&D93&"|"&G93&"|"&J93 -> НоваПак|План|Сервис|2|3 | T93: =A93&"|"&C93&"|"&G93 -> НоваПак|План|2 | U93: =IF(H93="да",A93&"|"&C93&"|"&D93&"|"&J93,"") | V93: =IF(C93="План",A93&"|"&J93,"") -> НоваПак|3
A94: НоваПак | B94: РФ | C94: План | D94: Сервис | E94: План и бонусы | F94: Размер бонуса по итогам 2026 г | G94: 2 | J94: 5 | M94: 0.01 | N94: % | O94: НоваПак | P94: H5 | Q94: =A94&"|"&C94&"|"&D94&"|"&G94 -> НоваПак|План|Сервис|2 | R94: =A94&"|"&C94&"|"&D94&"|"&J94 -> НоваПак|План|Сервис|5 | S94: =A94&"|"&C94&"|"&D94&"|"&G94&"|"&J94 -> НоваПак|План|Сервис|2|5 | T94: =A94&"|"&C94&"|"&G94 -> НоваПак|План|2 | U94: =IF(H94="да",A94&"|"&C94&"|"&D94&"|"&J94,"") | V94: =IF(C94="План",A94&"|"&J94,"") -> НоваПак|5
A95: НоваПак | B95: РФ | C95: План | D95: Сервис | E95: План и бонусы | F95: Скидка в 1 кв. 2026 ф.г.* | G95: 2 | J95: 6 | M95: 0.27 | N95: % | O95: НоваПак | P95: I5 | Q95: =A95&"|"&C95&"|"&D95&"|"&G95 -> НоваПак|План|Сервис|2 | R95: =A95&"|"&C95&"|"&D95&"|"&J95 -> НоваПак|План|Сервис|6 | S95: =A95&"|"&C95&"|"&D95&"|"&G95&"|"&J95 -> НоваПак|План|Сервис|2|6 | T95: =A95&"|"&C95&"|"&G95 -> НоваПак|План|2 | U95: =IF(H95="да",A95&"|"&C95&"|"&D95&"|"&J95,"") | V95: =IF(C95="План",A95&"|"&J95,"") -> НоваПак|6
A96: НоваПак | B96: РФ | C96: План | D96: Оборудование | E96: План и бонусы | F96: Выручка 2024 | G96: 3 | J96: 1 | M96: 912543 | N96: EUR | O96: НоваПак | P96: D6 | Q96: =A96&"|"&C96&"|"&D96&"|"&G96 -> НоваПак|План|Оборудование|3 | R96: =A96&"|"&C96&"|"&D96&"|"&J96 -> НоваПак|План|Оборудование|1 | S96: =A96&"|"&C96&"|"&D96&"|"&G96&"|"&J96 -> НоваПак|План|Оборудование|3|1 | T96: =A96&"|"&C96&"|"&G96 -> НоваПак|План|3 | U96: =IF(H96="да",A96&"|"&C96&"|"&D96&"|"&J96,"") | V96: =IF(C96="План",A96&"|"&J96,"") -> НоваПак|1
A97: НоваПак | B97: РФ | C97: План | D97: Оборудование | E97: План и бонусы | F97: Выручка 2025 | G97: 3 | J97: 2 | M97: 401117 | N97: EUR | O97: НоваПак | P97: E6 | Q97: =A97&"|"&C97&"|"&D97&"|"&G97 -> НоваПак|План|Оборудование|3 | R97: =A97&"|"&C97&"|"&D97&"|"&J97 -> НоваПак|План|Оборудование|2 | S97: =A97&"|"&C97&"|"&D97&"|"&G97&"|"&J97 -> НоваПак|План|Оборудование|3|2 | T97: =A97&"|"&C97&"|"&G97 -> НоваПак|План|3 | U97: =IF(H97="да",A97&"|"&C97&"|"&D97&"|"&J97,"") | V97: =IF(C97="План",A97&"|"&J97,"") -> НоваПак|2
A98: НоваПак | B98: РФ | C98: План | D98: Оборудование | E98: План и бонусы | F98: План 2026 | G98: 3 | J98: 3 | M98: 787000 | N98: EUR | O98: НоваПак | P98: F6 | Q98: =A98&"|"&C98&"|"&D98&"|"&G98 -> НоваПак|План|Оборудование|3 | R98: =A98&"|"&C98&"|"&D98&"|"&J98 -> НоваПак|План|Оборудование|3 | S98: =A98&"|"&C98&"|"&D98&"|"&G98&"|"&J98 -> НоваПак|План|Оборудование|3|3 | T98: =A98&"|"&C98&"|"&G98 -> НоваПак|План|3 | U98: =IF(H98="да",A98&"|"&C98&"|"&D98&"|"&J98,"") | V98: =IF(C98="План",A98&"|"&J98,"") -> НоваПак|3
... A105: НоваПак | B105: РФ | C105: План | D105: Расходные материалы | E105: План и бонусы | F105: Скидка в 1 кв. 2026 ф.г.* | G105: 4 | J105: 6 | M105: 0.02 | N105: % | O105: НоваПак | P105: I7 | Q105: =A105&"|"&C105&"|"&D105&"|"&G105 -> НоваПак|План|Расходные материалы|4 | R105: =A105&"|"&C105&"|"&D105&"|"&J105 -> НоваПак|План|Расходные материалы|6 | S105: =A105&"|"&C105&"|"&D105&"|"&G105&"|"&J105 -> НоваПак|План|Расходные материалы|4|6 | T105: =A105&"|"&C105&"|"&G105 -> НоваПак|План|4 | U105: =IF(H105="да",A105&"|"&C105&"|"&D105&"|"&J105,"") | V105: =IF(C105="План",A105&"|"&J105,"") -> НоваПак|6
A106: НоваПак | B106: РФ | C106: Шкала | D106: Оборудование | E106: Оборудование — за квартал | F106: 1 Базовое вознаграждение за Дилерский договор | G106: 1 | I106: до 75 | J106: 1 | M106: 0.06 | N106: % | O106: НоваПак | P106: E13 | Q106: =A106&"|"&C106&"|"&D106&"|"&G106 -> НоваПак|Шкала|Оборудование|1 | R106: =A106&"|"&C106&"|"&D106&"|"&J106 -> НоваПак|Шкала|Оборудование|1 | S106: =A106&"|"&C106&"|"&D106&"|"&G106&"|"&J106 -> НоваПак|Шкала|Оборудование|1|1 | T106: =A106&"|"&C106&"|"&G106 -> НоваПак|Шкала|1 | U106: =IF(H106="да",A106&"|"&C106&"|"&D106&"|"&J106,"") | V106: =IF(C106="План",A106&"|"&J106,"")
A107: НоваПак | B107: РФ | C107: Шкала | D107: Оборудование | E107: Оборудование — за квартал | F107: 1 Базовое вознаграждение за Дилерский договор | G107: 1 | I107: 75-114 | J107: 2 | M107: 0.06 | N107: % | O107: НоваПак | P107: F13 | Q107: =A107&"|"&C107&"|"&D107&"|"&G107 -> НоваПак|Шкала|Оборудование|1 | R107: =A107&"|"&C107&"|"&D107&"|"&J107 -> НоваПак|Шкала|Оборудование|2 | S107: =A107&"|"&C107&"|"&D107&"|"&G107&"|"&J107 -> НоваПак|Шкала|Оборудование|1|2 | T107: =A107&"|"&C107&"|"&G107 -> НоваПак|Шкала|1 | U107: =IF(H107="да",A107&"|"&C107&"|"&D107&"|"&J107,"") | V107: =IF(C107="План",A107&"|"&J107,"")
A108: НоваПак | B108: РФ | C108: Шкала | D108: Оборудование | E108: Оборудование — за квартал | F108: 1 Базовое вознаграждение за Дилерский договор | G108: 1 | I108: 115-149 | J108: 3 | M108: 0.06 | N108: % | O108: НоваПак | P108: G13 | Q108: =A108&"|"&C108&"|"&D108&"|"&G108 -> НоваПак|Шкала|Оборудование|1 | R108: =A108&"|"&C108&"|"&D108&"|"&J108 -> НоваПак|Шкала|Оборудование|3 | S108: =A108&"|"&C108&"|"&D108&"|"&G108&"|"&J108 -> НоваПак|Шкала|Оборудование|1|3 | T108: =A108&"|"&C108&"|"&G108 -> НоваПак|Шкала|1 | U108: =IF(H108="да",A108&"|"&C108&"|"&D108&"|"&J108,"") | V108: =IF(C108="План",A108&"|"&J108,"")
A109: НоваПак | B109: РФ | C109: Шкала | D109: Оборудование | E109: Оборудование — за квартал | F109: 1 Базовое вознаграждение за Дилерский договор | G109: 1 | I109: 150-189 | J109: 4 | M109: 0.06 | N109: % | O109: НоваПак | P109: H13 | Q109: =A109&"|"&C109&"|"&D109&"|"&G109 -> НоваПак|Шкала|Оборудование|1 | R109: =A109&"|"&C109&"|"&D109&"|"&J109 -> НоваПак|Шкала|Оборудование|4 | S109: =A109&"|"&C109&"|"&D109&"|"&G109&"|"&J109 -> НоваПак|Шкала|Оборудование|1|4 | T109: =A109&"|"&C109&"|"&G109 -> НоваПак|Шкала|1 | U109: =IF(H109="да",A109&"|"&C109&"|"&D109&"|"&J109,"") | V109: =IF(C109="План",A109&"|"&J109,"")
A110: НоваПак | B110: РФ | C110: Шкала | D110: Оборудование | E110: Оборудование — за квартал | F110: 1 Базовое вознаграждение за Дилерский договор | G110: 1 | I110: 190-224 | J110: 5 | M110: 0.06 | N110: % | O110: НоваПак | P110: I13 | Q110: =A110&"|"&C110&"|"&D110&"|"&G110 -> НоваПак|Шкала|Оборудование|1 | R110: =A110&"|"&C110&"|"&D110&"|"&J110 -> НоваПак|Шкала|Оборудование|5 | S110: =A110&"|"&C110&"|"&D110&"|"&G110&"|"&J110 -> НоваПак|Шкала|Оборудование|1|5 | T110: =A110&"|"&C110&"|"&G110 -> НоваПак|Шкала|1 | U110: =IF(H110="да",A110&"|"&C110&"|"&D110&"|"&J110,"") | V110: =IF(C110="План",A110&"|"&J110,"")
A111: НоваПак | B111: РФ | C111: Шкала | D111: Оборудование | E111: Оборудование — за квартал | F111: 1 Базовое вознаграждение за Дилерский договор | G111: 1 | I111: 225 и более | J111: 6 | M111: 0.06 | N111: % | O111: НоваПак | P111: J13 | Q111: =A111&"|"&C111&"|"&D111&"|"&G111 -> НоваПак|Шкала|Оборудование|1 | R111: =A111&"|"&C111&"|"&D111&"|"&J111 -> НоваПак|Шкала|Оборудование|6 | S111: =A111&"|"&C111&"|"&D111&"|"&G111&"|"&J111 -> НоваПак|Шкала|Оборудование|1|6 | T111: =A111&"|"&C111&"|"&G111 -> НоваПак|Шкала|1 | U111: =IF(H111="да",A111&"|"&C111&"|"&D111&"|"&J111,"") | V111: =IF(C111="План",A111&"|"&J111,"")
A112: НоваПак | B112: РФ | C112: Шкала | D112: Оборудование | E112: Оборудование — за квартал | F112: 2.1.1. Сервисный центр | G112: 2 | I112: до 75 | J112: 1 | M112: 0.06 | N112: % | O112: НоваПак | P112: E14 | Q112: =A112&"|"&C112&"|"&D112&"|"&G112 -> НоваПак|Шкала|Оборудование|2 | R112: =A112&"|"&C112&"|"&D112&"|"&J112 -> НоваПак|Шкала|Оборудование|1 | S112: =A112&"|"&C112&"|"&D112&"|"&G112&"|"&J112 -> НоваПак|Шкала|Оборудование|2|1 | T112: =A112&"|"&C112&"|"&G112 -> НоваПак|Шкала|2 | U112: =IF(H112="да",A112&"|"&C112&"|"&D112&"|"&J112,"") | V112: =IF(C112="План",A112&"|"&J112,"")
A113: НоваПак | B113: РФ | C113: Шкала | D113: Оборудование | E113: Оборудование — за квартал | F113: 2.1.1. Сервисный центр | G113: 2 | I113: 75-114 | J113: 2 | M113: 0.06 | N113: % | O113: НоваПак | P113: F14 | Q113: =A113&"|"&C113&"|"&D113&"|"&G113 -> НоваПак|Шкала|Оборудование|2 | R113: =A113&"|"&C113&"|"&D113&"|"&J113 -> НоваПак|Шкала|Оборудование|2 | S113: =A113&"|"&C113&"|"&D113&"|"&G113&"|"&J113 -> НоваПак|Шкала|Оборудование|2|2 | T113: =A113&"|"&C113&"|"&G113 -> НоваПак|Шкала|2 | U113: =IF(H113="да",A113&"|"&C113&"|"&D113&"|"&J113,"") | V113: =IF(C113="План",A113&"|"&J113,"")
A114: НоваПак | B114: РФ | C114: Шкала | D114: Оборудование | E114: Оборудование — за квартал | F114: 2.1.1. Сервисный центр | G114: 2 | I114: 115-149 | J114: 3 | M114: 0.06 | N114: % | O114: НоваПак | P114: G14 | Q114: =A114&"|"&C114&"|"&D114&"|"&G114 -> НоваПак|Шкала|Оборудование|2 | R114: =A114&"|"&C114&"|"&D114&"|"&J114 -> НоваПак|Шкала|Оборудование|3 | S114: =A114&"|"&C114&"|"&D114&"|"&G114&"|"&J114 -> НоваПак|Шкала|Оборудование|2|3 | T114: =A114&"|"&C114&"|"&G114 -> НоваПак|Шкала|2 | U114: =IF(H114="да",A114&"|"&C114&"|"&D114&"|"&J114,"") | V114: =IF(C114="План",A114&"|"&J114,"")
A115: НоваПак | B115: РФ | C115: Шкала | D115: Оборудование | E115: Оборудование — за квартал | F115: 2.1.1. Сервисный центр | G115: 2 | I115: 150-189 | J115: 4 | M115: 0.06 | N115: % | O115: НоваПак | P115: H14 | Q115: =A115&"|"&C115&"|"&D115&"|"&G115 -> НоваПак|Шкала|Оборудование|2 | R115: =A115&"|"&C115&"|"&D115&"|"&J115 -> НоваПак|Шкала|Оборудование|4 | S115: =A115&"|"&C115&"|"&D115&"|"&G115&"|"&J115 -> НоваПак|Шкала|Оборудование|2|4 | T115: =A115&"|"&C115&"|"&G115 -> НоваПак|Шкала|2 | U115: =IF(H115="да",A115&"|"&C115&"|"&D115&"|"&J115,"") | V115: =IF(C115="План",A115&"|"&J115,"")
A116: НоваПак | B116: РФ | C116: Шкала | D116: Оборудование | E116: Оборудование — за квартал | F116: 2.1.1. Сервисный центр | G116: 2 | I116: 190-224 | J116: 5 | M116: 0.06 | N116: % | O116: НоваПак | P116: I14 | Q116: =A116&"|"&C116&"|"&D116&"|"&G116 -> НоваПак|Шкала|Оборудование|2 | R116: =A116&"|"&C116&"|"&D116&"|"&J116 -> НоваПак|Шкала|Оборудование|5 | S116: =A116&"|"&C116&"|"&D116&"|"&G116&"|"&J116 -> НоваПак|Шкала|Оборудование|2|5 | T116: =A116&"|"&C116&"|"&G116 -> НоваПак|Шкала|2 | U116: =IF(H116="да",A116&"|"&C116&"|"&D116&"|"&J116,"") | V116: =IF(C116="План",A116&"|"&J116,"")
A117: НоваПак | B117: РФ | C117: Шкала | D117: Оборудование | E117: Оборудование — за квартал | F117: 2.1.1. Сервисный центр | G117: 2 | I117: 225 и более | J117: 6 | M117: 0.06 | N117: % | O117: НоваПак | P117: J14 | Q117: =A117&"|"&C117&"|"&D117&"|"&G117 -> НоваПак|Шкала|Оборудование|2 | R117: =A117&"|"&C117&"|"&D117&"|"&J117 -> НоваПак|Шкала|Оборудование|6 | S117: =A117&"|"&C117&"|"&D117&"|"&G117&"|"&J117 -> НоваПак|Шкала|Оборудование|2|6 | T117: =A117&"|"&C117&"|"&G117 -> НоваПак|Шкала|2 | U117: =IF(H117="да",A117&"|"&C117&"|"&D117&"|"&J117,"") | V117: =IF(C117="План",A117&"|"&J117,"")
... A135: НоваПак | B135: РФ | C135: Шкала | D135: Оборудование | E135: Оборудование — за квартал | F135: 3 Объем закупок МП | G135: 5 | I135: 225 и более | J135: 6 | M135: 0.05 | N135: % | O135: НоваПак | P135: J17 | Q135: =A135&"|"&C135&"|"&D135&"|"&G135 -> НоваПак|Шкала|Оборудование|5 | R135: =A135&"|"&C135&"|"&D135&"|"&J135 -> НоваПак|Шкала|Оборудование|6 | S135: =A135&"|"&C135&"|"&D135&"|"&G135&"|"&J135 -> НоваПак|Шкала|Оборудование|5|6 | T135: =A135&"|"&C135&"|"&G135 -> НоваПак|Шкала|5 | U135: =IF(H135="да",A135&"|"&C135&"|"&D135&"|"&J135,"") | V135: =IF(C135="План",A135&"|"&J135,"")
A136: НоваПак | B136: РФ | C136: Шкала | D136: Оборудование | E136: Оборудование — за квартал | F136: ИТОГО по МП: | G136: 6 | H136: да | I136: до 75 | J136: 1 | M136: 0.14 | N136: % | O136: НоваПак | P136: E18 | Q136: =A136&"|"&C136&"|"&D136&"|"&G136 -> НоваПак|Шкала|Оборудование|6 | R136: =A136&"|"&C136&"|"&D136&"|"&J136 -> НоваПак|Шкала|Оборудование|1 | S136: =A136&"|"&C136&"|"&D136&"|"&G136&"|"&J136 -> НоваПак|Шкала|Оборудование|6|1 | T136: =A136&"|"&C136&"|"&G136 -> НоваПак|Шкала|6 | U136: =IF(H136="да",A136&"|"&C136&"|"&D136&"|"&J136,"") -> НоваПак|Шкала|Оборудование|1 | V136: =IF(C136="План",A136&"|"&J136,"")
A137: НоваПак | B137: РФ | C137: Шкала | D137: Оборудование | E137: Оборудование — за квартал | F137: ИТОГО по МП: | G137: 6 | H137: да | I137: 75-114 | J137: 2 | M137: 0.15 | N137: % | O137: НоваПак | P137: F18 | Q137: =A137&"|"&C137&"|"&D137&"|"&G137 -> НоваПак|Шкала|Оборудование|6 | R137: =A137&"|"&C137&"|"&D137&"|"&J137 -> НоваПак|Шкала|Оборудование|2 | S137: =A137&"|"&C137&"|"&D137&"|"&G137&"|"&J137 -> НоваПак|Шкала|Оборудование|6|2 | T137: =A137&"|"&C137&"|"&G137 -> НоваПак|Шкала|6 | U137: =IF(H137="да",A137&"|"&C137&"|"&D137&"|"&J137,"") -> НоваПак|Шкала|Оборудование|2 | V137: =IF(C137="План",A137&"|"&J137,"")
A138: НоваПак | B138: РФ | C138: Шкала | D138: Оборудование | E138: Оборудование — за квартал | F138: ИТОГО по МП: | G138: 6 | H138: да | I138: 115-149 | J138: 3 | M138: 0.16 | N138: % | O138: НоваПак | P138: G18 | Q138: =A138&"|"&C138&"|"&D138&"|"&G138 -> НоваПак|Шкала|Оборудование|6 | R138: =A138&"|"&C138&"|"&D138&"|"&J138 -> НоваПак|Шкала|Оборудование|3 | S138: =A138&"|"&C138&"|"&D138&"|"&G138&"|"&J138 -> НоваПак|Шкала|Оборудование|6|3 | T138: =A138&"|"&C138&"|"&G138 -> НоваПак|Шкала|6 | U138: =IF(H138="да",A138&"|"&C138&"|"&D138&"|"&J138,"") -> НоваПак|Шкала|Оборудование|3 | V138: =IF(C138="План",A138&"|"&J138,"")
A139: НоваПак | B139: РФ | C139: Шкала | D139: Оборудование | E139: Оборудование — за квартал | F139: ИТОГО по МП: | G139: 6 | H139: да | I139: 150-189 | J139: 4 | M139: 0.17 | N139: % | O139: НоваПак | P139: H18 | Q139: =A139&"|"&C139&"|"&D139&"|"&G139 -> НоваПак|Шкала|Оборудование|6 | R139: =A139&"|"&C139&"|"&D139&"|"&J139 -> НоваПак|Шкала|Оборудование|4 | S139: =A139&"|"&C139&"|"&D139&"|"&G139&"|"&J139 -> НоваПак|Шкала|Оборудование|6|4 | T139: =A139&"|"&C139&"|"&G139 -> НоваПак|Шкала|6 | U139: =IF(H139="да",A139&"|"&C139&"|"&D139&"|"&J139,"") -> НоваПак|Шкала|Оборудование|4 | V139: =IF(C139="План",A139&"|"&J139,"")
A140: НоваПак | B140: РФ | C140: Шкала | D140: Оборудование | E140: Оборудование — за квартал | F140: ИТОГО по МП: | G140: 6 | H140: да | I140: 190-224 | J140: 5 | M140: 0.18 | N140: % | O140: НоваПак | P140: I18 | Q140: =A140&"|"&C140&"|"&D140&"|"&G140 -> НоваПак|Шкала|Оборудование|6 | R140: =A140&"|"&C140&"|"&D140&"|"&J140 -> НоваПак|Шкала|Оборудование|5 | S140: =A140&"|"&C140&"|"&D140&"|"&G140&"|"&J140 -> НоваПак|Шкала|Оборудование|6|5 | T140: =A140&"|"&C140&"|"&G140 -> НоваПак|Шкала|6 | U140: =IF(H140="да",A140&"|"&C140&"|"&D140&"|"&J140,"") -> НоваПак|Шкала|Оборудование|5 | V140: =IF(C140="План",A140&"|"&J140,"")
A141: НоваПак | B141: РФ | C141: Шкала | D141: Оборудование | E141: Оборудование — за квартал | F141: ИТОГО по МП: | G141: 6 | H141: да | I141: 225 и более | J141: 6 | M141: 0.19 | N141: % | O141: НоваПак | P141: J18 | Q141: =A141&"|"&C141&"|"&D141&"|"&G141 -> НоваПак|Шкала|Оборудование|6 | R141: =A141&"|"&C141&"|"&D141&"|"&J141 -> НоваПак|Шкала|Оборудование|6 | S141: =A141&"|"&C141&"|"&D141&"|"&G141&"|"&J141 -> НоваПак|Шкала|Оборудование|6|6 | T141: =A141&"|"&C141&"|"&G141 -> НоваПак|Шкала|6 | U141: =IF(H141="да",A141&"|"&C141&"|"&D141&"|"&J141,"") -> НоваПак|Шкала|Оборудование|6 | V141: =IF(C141="План",A141&"|"&J141,"")
A142: НоваПак | B142: РФ | C142: Шкала | D142: Оборудование | E142: Оборудование — за квартал | F142: Наличие минимальных складских остатков по РМ (синхронизация отчета по остаткам с 1С КОМПО) | G142: 7 | I142: до 75 | J142: 1 | M142: 0.01 | N142: % | O142: НоваПак | P142: E20 | Q142: =A142&"|"&C142&"|"&D142&"|"&G142 -> НоваПак|Шкала|Оборудование|7 | R142: =A142&"|"&C142&"|"&D142&"|"&J142 -> НоваПак|Шкала|Оборудование|1 | S142: =A142&"|"&C142&"|"&D142&"|"&G142&"|"&J142 -> НоваПак|Шкала|Оборудование|7|1 | T142: =A142&"|"&C142&"|"&G142 -> НоваПак|Шкала|7 | U142: =IF(H142="да",A142&"|"&C142&"|"&D142&"|"&J142,"") | V142: =IF(C142="План",A142&"|"&J142,"")
A143: НоваПак | B143: РФ | C143: Шкала | D143: Оборудование | E143: Оборудование — за квартал | F143: Наличие минимальных складских остатков по РМ (синхронизация отчета по остаткам с 1С КОМПО) | G143: 7 | I143: 75-114 | J143: 2 | M143: 0.01 | N143: % | O143: НоваПак | P143: F20 | Q143: =A143&"|"&C143&"|"&D143&"|"&G143 -> НоваПак|Шкала|Оборудование|7 | R143: =A143&"|"&C143&"|"&D143&"|"&J143 -> НоваПак|Шкала|Оборудование|2 | S143: =A143&"|"&C143&"|"&D143&"|"&G143&"|"&J143 -> НоваПак|Шкала|Оборудование|7|2 | T143: =A143&"|"&C143&"|"&G143 -> НоваПак|Шкала|7 | U143: =IF(H143="да",A143&"|"&C143&"|"&D143&"|"&J143,"") | V143: =IF(C143="План",A143&"|"&J143,"")
A144: НоваПак | B144: РФ | C144: Шкала | D144: Оборудование | E144: Оборудование — за квартал | F144: Наличие минимальных складских остатков по РМ (синхронизация отчета по остаткам с 1С КОМПО) | G144: 7 | I144: 115-149 | J144: 3 | M144: 0.01 | N144: % | O144: НоваПак | P144: G20 | Q144: =A144&"|"&C144&"|"&D144&"|"&G144 -> НоваПак|Шкала|Оборудование|7 | R144: =A144&"|"&C144&"|"&D144&"|"&J144 -> НоваПак|Шкала|Оборудование|3 | S144: =A144&"|"&C144&"|"&D144&"|"&G144&"|"&J144 -> НоваПак|Шкала|Оборудование|7|3 | T144: =A144&"|"&C144&"|"&G144 -> НоваПак|Шкала|7 | U144: =IF(H144="да",A144&"|"&C144&"|"&D144&"|"&J144,"") | V144: =IF(C144="План",A144&"|"&J144,"")
A145: НоваПак | B145: РФ | C145: Шкала | D145: Оборудование | E145: Оборудование — за квартал | F145: Наличие минимальных складских остатков по РМ (синхронизация отчета по остаткам с 1С КОМПО) | G145: 7 | I145: 150-189 | J145: 4 | M145: 0.01 | N145: % | O145: НоваПак | P145: H20 | Q145: =A145&"|"&C145&"|"&D145&"|"&G145 -> НоваПак|Шкала|Оборудование|7 | R145: =A145&"|"&C145&"|"&D145&"|"&J145 -> НоваПак|Шкала|Оборудование|4 | S145: =A145&"|"&C145&"|"&D145&"|"&G145&"|"&J145 -> НоваПак|Шкала|Оборудование|7|4 | T145: =A145&"|"&C145&"|"&G145 -> НоваПак|Шкала|7 | U145: =IF(H145="да",A145&"|"&C145&"|"&D145&"|"&J145,"") | V145: =IF(C145="План",A145&"|"&J145,"")
A146: НоваПак | B146: РФ | C146: Шкала | D146: Оборудование | E146: Оборудование — за квартал | F146: Наличие минимальных складских остатков по РМ (синхронизация отчета по остаткам с 1С КОМПО) | G146: 7 | I146: 190-224 | J146: 5 | M146: 0.01 | N146: % | O146: НоваПак | P146: I20 | Q146: =A146&"|"&C146&"|"&D146&"|"&G146 -> НоваПак|Шкала|Оборудование|7 | R146: =A146&"|"&C146&"|"&D146&"|"&J146 -> НоваПак|Шкала|Оборудование|5 | S146: =A146&"|"&C146&"|"&D146&"|"&G146&"|"&J146 -> НоваПак|Шкала|Оборудование|7|5 | T146: =A146&"|"&C146&"|"&G146 -> НоваПак|Шкала|7 | U146: =IF(H146="да",A146&"|"&C146&"|"&D146&"|"&J146,"") | V146: =IF(C146="План",A146&"|"&J146,"")
A147: НоваПак | B147: РФ | C147: Шкала | D147: Оборудование | E147: Оборудование — за квартал | F147: Наличие минимальных складских остатков по РМ (синхронизация отчета по остаткам с 1С КОМПО) | G147: 7 | I147: 225 и более | J147: 6 | M147: 0.01 | N147: % | O147: НоваПак | P147: J20 | Q147: =A147&"|"&C147&"|"&D147&"|"&G147 -> НоваПак|Шкала|Оборудование|7 | R147: =A147&"|"&C147&"|"&D147&"|"&J147 -> НоваПак|Шкала|Оборудование|6 | S147: =A147&"|"&C147&"|"&D147&"|"&G147&"|"&J147 -> НоваПак|Шкала|Оборудование|7|6 | T147: =A147&"|"&C147&"|"&G147 -> НоваПак|Шкала|7 | U147: =IF(H147="да",A147&"|"&C147&"|"&D147&"|"&J147,"") | V147: =IF(C147="План",A147&"|"&J147,"")
A148: НоваПак | B148: РФ | C148: Шкала | D148: Оборудование | E148: Оборудование — за квартал | F148: Объем закупок РМ | G148: 8 | I148: до 75 | J148: 1 | M148: 0 | N148: % | O148: НоваПак | P148: E21 | Q148: =A148&"|"&C148&"|"&D148&"|"&G148 -> НоваПак|Шкала|Оборудование|8 | R148: =A148&"|"&C148&"|"&D148&"|"&J148 -> НоваПак|Шкала|Оборудование|1 | S148: =A148&"|"&C148&"|"&D148&"|"&G148&"|"&J148 -> НоваПак|Шкала|Оборудование|8|1 | T148: =A148&"|"&C148&"|"&G148 -> НоваПак|Шкала|8 | U148: =IF(H148="да",A148&"|"&C148&"|"&D148&"|"&J148,"") | V148: =IF(C148="План",A148&"|"&J148,"")
A149: НоваПак | B149: РФ | C149: Шкала | D149: Оборудование | E149: Оборудование — за квартал | F149: Объем закупок РМ | G149: 8 | I149: 75-114 | J149: 2 | M149: 0.01 | N149: % | O149: НоваПак | P149: F21 | Q149: =A149&"|"&C149&"|"&D149&"|"&G149 -> НоваПак|Шкала|Оборудование|8 | R149: =A149&"|"&C149&"|"&D149&"|"&J149 -> НоваПак|Шкала|Оборудование|2 | S149: =A149&"|"&C149&"|"&D149&"|"&G149&"|"&J149 -> НоваПак|Шкала|Оборудование|8|2 | T149: =A149&"|"&C149&"|"&G149 -> НоваПак|Шкала|8 | U149: =IF(H149="да",A149&"|"&C149&"|"&D149&"|"&J149,"") | V149: =IF(C149="План",A149&"|"&J149,"")
A150: НоваПак | B150: РФ | C150: Шкала | D150: Оборудование | E150: Оборудование — за квартал | F150: Объем закупок РМ | G150: 8 | I150: 115-149 | J150: 3 | M150: 0.02 | N150: % | O150: НоваПак | P150: G21 | Q150: =A150&"|"&C150&"|"&D150&"|"&G150 -> НоваПак|Шкала|Оборудование|8 | R150: =A150&"|"&C150&"|"&D150&"|"&J150 -> НоваПак|Шкала|Оборудование|3 | S150: =A150&"|"&C150&"|"&D150&"|"&G150&"|"&J150 -> НоваПак|Шкала|Оборудование|8|3 | T150: =A150&"|"&C150&"|"&G150 -> НоваПак|Шкала|8 | U150: =IF(H150="да",A150&"|"&C150&"|"&D150&"|"&J150,"") | V150: =IF(C150="План",A150&"|"&J150,"")
A151: НоваПак | B151: РФ | C151: Шкала | D151: Оборудование | E151: Оборудование — за квартал | F151: Объем закупок РМ | G151: 8 | I151: 150-189 | J151: 4 | M151: 0.03 | N151: % | O151: НоваПак | P151: H21 | Q151: =A151&"|"&C151&"|"&D151&"|"&G151 -> НоваПак|Шкала|Оборудование|8 | R151: =A151&"|"&C151&"|"&D151&"|"&J151 -> НоваПак|Шкала|Оборудование|4 | S151: =A151&"|"&C151&"|"&D151&"|"&G151&"|"&J151 -> НоваПак|Шкала|Оборудование|8|4 | T151: =A151&"|"&C151&"|"&G151 -> НоваПак|Шкала|8 | U151: =IF(H151="да",A151&"|"&C151&"|"&D151&"|"&J151,"") | V151: =IF(C151="План",A151&"|"&J151,"")
A152: НоваПак | B152: РФ | C152: Шкала | D152: Оборудование | E152: Оборудование — за квартал | F152: Объем закупок РМ | G152: 8 | I152: 190-224 | J152: 5 | M152: 0.04 | N152: % | O152: НоваПак | P152: I21 | Q152: =A152&"|"&C152&"|"&D152&"|"&G152 -> НоваПак|Шкала|Оборудование|8 | R152: =A152&"|"&C152&"|"&D152&"|"&J152 -> НоваПак|Шкала|Оборудование|5 | S152: =A152&"|"&C152&"|"&D152&"|"&G152&"|"&J152 -> НоваПак|Шкала|Оборудование|8|5 | T152: =A152&"|"&C152&"|"&G152 -> НоваПак|Шкала|8 | U152: =IF(H152="да",A152&"|"&C152&"|"&D152&"|"&J152,"") | V152: =IF(C152="План",A152&"|"&J152,"")
A153: НоваПак | B153: РФ | C153: Шкала | D153: Оборудование | E153: Оборудование — за квартал | F153: Объем закупок РМ | G153: 8 | I153: 225 и более | J153: 6 | M153: 0.05 | N153: % | O153: НоваПак | P153: J21 | Q153: =A153&"|"&C153&"|"&D153&"|"&G153 -> НоваПак|Шкала|Оборудование|8 | R153: =A153&"|"&C153&"|"&D153&"|"&J153 -> НоваПак|Шкала|Оборудование|6 | S153: =A153&"|"&C153&"|"&D153&"|"&G153&"|"&J153 -> НоваПак|Шкала|Оборудование|8|6 | T153: =A153&"|"&C153&"|"&G153 -> НоваПак|Шкала|8 | U153: =IF(H153="да",A153&"|"&C153&"|"&D153&"|"&J153,"") | V153: =IF(C153="План",A153&"|"&J153,"")
... A165: НоваПак | B165: РФ | C165: Шкала | D165: Расходные материалы | E165: Расходные материалы — за квартал | F165: Объем закупок РМ | G165: 2 | I165: 225 и более | J165: 6 | M165: 0.05 | N165: % | O165: НоваПак | P165: J21 | Q165: =A165&"|"&C165&"|"&D165&"|"&G165 -> НоваПак|Шкала|Расходные материалы|2 | R165: =A165&"|"&C165&"|"&D165&"|"&J165 -> НоваПак|Шкала|Расходные материалы|6 | S165: =A165&"|"&C165&"|"&D165&"|"&G165&"|"&J165 -> НоваПак|Шкала|Расходные материалы|2|6 | T165: =A165&"|"&C165&"|"&G165 -> НоваПак|Шкала|2 | U165: =IF(H165="да",A165&"|"&C165&"|"&D165&"|"&J165,"") | V165: =IF(C165="План",A165&"|"&J165,"")
A166: НоваПак | B166: РФ | C166: Шкала | D166: Сервис (ЗЧ) | E166: Сервис (ЗЧ) — расчёт по парку оборудования | F166: Скидка по сервису | G166: 1 | H166: да | I166: 0–500 | J166: 1 | K166: 0 | L166: 500 | M166: 0.19 | N166: % | O166: НоваПак | P166: F26 | Q166: =A166&"|"&C166&"|"&D166&"|"&G166 -> НоваПак|Шкала|Сервис (ЗЧ)|1 | R166: =A166&"|"&C166&"|"&D166&"|"&J166 -> НоваПак|Шкала|Сервис (ЗЧ)|1 | S166: =A166&"|"&C166&"|"&D166&"|"&G166&"|"&J166 -> НоваПак|Шкала|Сервис (ЗЧ)|1|1 | T166: =A166&"|"&C166&"|"&G166 -> НоваПак|Шкала|1 | U166: =IF(H166="да",A166&"|"&C166&"|"&D166&"|"&J166,"") -> НоваПак|Шкала|Сервис (ЗЧ)|1 | V166: =IF(C166="План",A166&"|"&J166,"")
A167: НоваПак | B167: РФ | C167: Шкала | D167: Сервис (ЗЧ) | E167: Сервис (ЗЧ) — расчёт по парку оборудования | F167: Скидка по сервису | G167: 1 | H167: да | I167: 501–1000 | J167: 2 | K167: 501 | L167: 1000 | M167: 0.21 | N167: % | O167: НоваПак | P167: F27 | Q167: =A167&"|"&C167&"|"&D167&"|"&G167 -> НоваПак|Шкала|Сервис (ЗЧ)|1 | R167: =A167&"|"&C167&"|"&D167&"|"&J167 -> НоваПак|Шкала|Сервис (ЗЧ)|2 | S167: =A167&"|"&C167&"|"&D167&"|"&G167&"|"&J167 -> НоваПак|Шкала|Сервис (ЗЧ)|1|2 | T167: =A167&"|"&C167&"|"&G167 -> НоваПак|Шкала|1 | U167: =IF(H167="да",A167&"|"&C167&"|"&D167&"|"&J167,"") -> НоваПак|Шкала|Сервис (ЗЧ)|2 | V167: =IF(C167="План",A167&"|"&J167,"")
A168: НоваПак | B168: РФ | C168: Шкала | D168: Сервис (ЗЧ) | E168: Сервис (ЗЧ) — расчёт по парку оборудования | F168: Скидка по сервису | G168: 1 | H168: да | I168: 1001–1800 | J168: 3 | K168: 1001 | L168: 1800 | M168: 0.23 | N168: % | O168: НоваПак | P168: F28 | Q168: =A168&"|"&C168&"|"&D168&"|"&G168 -> НоваПак|Шкала|Сервис (ЗЧ)|1 | R168: =A168&"|"&C168&"|"&D168&"|"&J168 -> НоваПак|Шкала|Сервис (ЗЧ)|3 | S168: =A168&"|"&C168&"|"&D168&"|"&G168&"|"&J168 -> НоваПак|Шкала|Сервис (ЗЧ)|1|3 | T168: =A168&"|"&C168&"|"&G168 -> НоваПак|Шкала|1 | U168: =IF(H168="да",A168&"|"&C168&"|"&D168&"|"&J168,"") -> НоваПак|Шкала|Сервис (ЗЧ)|3 | V168: =IF(C168="План",A168&"|"&J168,"")
...

Sheet Витрина
A1: ### ВИТРИНА • здесь всё считается формулами из листа «Шкалы». Править нужно там — витрина обновится сама. Лист справочный: калькулятор его не читает.
A2: Выберите дилера в ячейке B4 — ниже появятся его план и бонусы, шкала оборудования, расходных материалов и сервиса. В конце листа — сравнение всех дилеров по строке ИТОГО.
W3: Список дилеров — служебный: источник выпадающего списка в B4, пересобирается скриптом
A4: Дилер: | B4: КОМПО Технолоджис | E4: Тип: | F4: =IFERROR(INDEX('Шкалы'!$B:$B,MATCH($B$4,'Шкалы'!$A:$A,0)),"") -> РФ | G4: Отчётность: | H4: =IF($F$4="РФ","за квартал","за полугодие") -> за квартал | I4: Сервис (ЗЧ): | J4: =IFERROR(INDEX('Шкалы'!$E:$E,MATCH($B$4&"|"&"Шкала"&"|"&"Сервис (ЗЧ)"&"|"&1&"|"&1,'Шкалы'!$S:$S,0)),"") -> Сервис (ЗЧ) — расчёт по парку оборудования | W4: КОМПО Технолоджис
W5: НоваПак
A6: ПЛАН И БОНУСЫ | W6: КСП (КОМПО-СП)
A7: Категория | B7: =IFERROR(INDEX('Шкалы'!$F:$F,MATCH($B$4&"|"&1,'Шкалы'!$V:$V,0)),"") -> Выручка 2024 | C7: =IFERROR(INDEX('Шкалы'!$F:$F,MATCH($B$4&"|"&2,'Шкалы'!$V:$V,0)),"") -> Выручка 2025 | D7: =IFERROR(INDEX('Шкалы'!$F:$F,MATCH($B$4&"|"&3,'Шкалы'!$V:$V,0)),"") -> План 2026 | E7: =IFERROR(INDEX('Шкалы'!$F:$F,MATCH($B$4&"|"&4,'Шкалы'!$V:$V,0)),"") -> Прирост П/Ф | F7: =IFERROR(INDEX('Шкалы'!$F:$F,MATCH($B$4&"|"&5,'Шкалы'!$V:$V,0)),"") -> Размер бонуса по итогам 2026 г | G7: =IFERROR(INDEX('Шкалы'!$F:$F,MATCH($B$4&"|"&6,'Шкалы'!$V:$V,0)),"") -> Скидка в 1 кв. 2026 ф.г.* | W7: Богатовъ Торговый Дом, Челябинск
A8: =IFERROR(INDEX('Шкалы'!$D:$D,MATCH($B$4&"|"&"План"&"|"&1,'Шкалы'!$T:$T,0)),"") -> Итого по дилеру | B8: =IFERROR(INDEX('Шкалы'!$M:$M,MATCH($B$4&"|"&"План"&"|"&$A8&"|"&1&"|"&1,'Шкалы'!$S:$S,0)),"") -> 4164812 | C8: =IFERROR(INDEX('Шкалы'!$M:$M,MATCH($B$4&"|"&"План"&"|"&$A8&"|"&1&"|"&2,'Шкалы'!$S:$S,0)),"") -> 4121760 | D8: =IFERROR(INDEX('Шкалы'!$M:$M,MATCH($B$4&"|"&"План"&"|"&$A8&"|"&1&"|"&3,'Шкалы'!$S:$S,0)),"") -> 4142912 | E8: =IFERROR(INDEX('Шкалы'!$M:$M,MATCH($B$4&"|"&"План"&"|"&$A8&"|"&1&"|"&4,'Шкалы'!$S:$S,0)),"") -> 0.0051317859 | F8: =IFERROR(INDEX('Шкалы'!$M:$M,MATCH($B$4&"|"&"План"&"|"&$A8&"|"&1&"|"&5,'Шкалы'!$S:$S,0)),"") | G8: =IFERROR(INDEX('Шкалы'!$M:$M,MATCH($B$4&"|"&"План"&"|"&$A8&"|"&1&"|"&6,'Шкалы'!$S:$S,0)),"") | W8: ASIAN BUSINESS SOLUTIONS, Узбекистан
A9: =IFERROR(INDEX('Шкалы'!$D:$D,MATCH($B$4&"|"&"План"&"|"&2,'Шкалы'!$T:$T,0)),"") -> Сервис | B9: =IFERROR(INDEX('Шкалы'!$M:$M,MATCH($B$4&"|"&"План"&"|"&$A9&"|"&2&"|"&1,'Шкалы'!$S:$S,0)),"") -> 346883 | C9: =IFERROR(INDEX('Шкалы'!$M:$M,MATCH($B$4&"|"&"План"&"|"&$A9&"|"&2&"|"&2,'Шкалы'!$S:$S,0)),"") -> 448343 | D9: =IFERROR(INDEX('Шкалы'!$M:$M,MATCH($B$4&"|"&"План"&"|"&$A9&"|"&2&"|"&3,'Шкалы'!$S:$S,0)),"") -> 480438 | E9: =IFERROR(INDEX('Шкалы'!$M:$M,MATCH($B$4&"|"&"План"&"|"&$A9&"|"&2&"|"&4,'Шкалы'!$S:$S,0)),"") | F9: =IFERROR(INDEX('Шкалы'!$M:$M,MATCH($B$4&"|"&"План"&"|"&$A9&"|"&2&"|"&5,'Шкалы'!$S:$S,0)),"") -> 0.01 | G9: =IFERROR(INDEX('Шкалы'!$M:$M,MATCH($B$4&"|"&"План"&"|"&$A9&"|"&2&"|"&6,'Шкалы'!$S:$S,0)),"") -> 0.3 | W9: Deling food
A10: =IFERROR(INDEX('Шкалы'!$D:$D,MATCH($B$4&"|"&"План"&"|"&3,'Шкалы'!$T:$T,0)),"") -> Оборудование | B10: =IFERROR(INDEX('Шкалы'!$M:$M,MATCH($B$4&"|"&"План"&"|"&$A10&"|"&3&"|"&1,'Шкалы'!$S:$S,0)),"") -> 2205660 | C10: =IFERROR(INDEX('Шкалы'!$M:$M,MATCH($B$4&"|"&"План"&"|"&$A10&"|"&3&"|"&2,'Шкалы'!$S:$S,0)),"") -> 1710368 | D10: =IFERROR(INDEX('Шкалы'!$M:$M,MATCH($B$4&"|"&"План"&"|"&$A10&"|"&3&"|"&3,'Шкалы'!$S:$S,0)),"") -> 2020593.8 | E10: =IFERROR(INDEX('Шкалы'!$M:$M,MATCH($B$4&"|"&"План"&"|"&$A10&"|"&3&"|"&4,'Шкалы'!$S:$S,0)),"") | F10: =IFERROR(INDEX('Шкалы'!$M:$M,MATCH($B$4&"|"&"План"&"|"&$A10&"|"&3&"|"&5,'Шкалы'!$S:$S,0)),"") -> 0.015 | G10: =IFERROR(INDEX('Шкалы'!$M:$M,MATCH($B$4&"|"&"План"&"|"&$A10&"|"&3&"|"&6,'Шкалы'!$S:$S,0)),"") -> 0.19 | W10: VitLine, Казахстан
A11: =IFERROR(INDEX('Шкалы'!$D:$D,MATCH($B$4&"|"&"План"&"|"&4,'Шкалы'!$T:$T,0)),"") -> Расходные материалы | B11: =IFERROR(INDEX('Шкалы'!$M:$M,MATCH($B$4&"|"&"План"&"|"&$A11&"|"&4&"|"&1,'Шкалы'!$S:$S,0)),"") -> 1612269 | C11: =IFERROR(INDEX('Шкалы'!$M:$M,MATCH($B$4&"|"&"План"&"|"&$A11&"|"&4&"|"&2,'Шкалы'!$S:$S,0)),"") -> 1963049 | D11: =IFERROR(INDEX('Шкалы'!$M:$M,MATCH($B$4&"|"&"План"&"|"&$A11&"|"&4&"|"&3,'Шкалы'!$S:$S,0)),"") -> 1641880.2 | E11: =IFERROR(INDEX('Шкалы'!$M:$M,MATCH($B$4&"|"&"План"&"|"&$A11&"|"&4&"|"&4,'Шкалы'!$S:$S,0)),"") | F11: =IFERROR(INDEX('Шкалы'!$M:$M,MATCH($B$4&"|"&"План"&"|"&$A11&"|"&4&"|"&5,'Шкалы'!$S:$S,0)),"") -> 0.005 | G11: =IFERROR(INDEX('Шкалы'!$M:$M,MATCH($B$4&"|"&"План"&"|"&$A11&"|"&4&"|"&6,'Шкалы'!$S:$S,0)),"") -> 0.06 | W11: UNIVERSAL MEAT
A12: =IFERROR(INDEX('Шкалы'!$D:$D,MATCH($B$4&"|"&"План"&"|"&5,'Шкалы'!$T:$T,0)),"") | B12: =IFERROR(INDEX('Шкалы'!$M:$M,MATCH($B$4&"|"&"План"&"|"&$A12&"|"&5&"|"&1,'Шкалы'!$S:$S,0)),"") | C12: =IFERROR(INDEX('Шкалы'!$M:$M,MATCH($B$4&"|"&"План"&"|"&$A12&"|"&5&"|"&2,'Шкалы'!$S:$S,0)),"") | D12: =IFERROR(INDEX('Шкалы'!$M:$M,MATCH($B$4&"|"&"План"&"|"&$A12&"|"&5&"|"&3,'Шкалы'!$S:$S,0)),"") | E12: =IFERROR(INDEX('Шкалы'!$M:$M,MATCH($B$4&"|"&"План"&"|"&$A12&"|"&5&"|"&4,'Шкалы'!$S:$S,0)),"") | F12: =IFERROR(INDEX('Шкалы'!$M:$M,MATCH($B$4&"|"&"План"&"|"&$A12&"|"&5&"|"&5,'Шкалы'!$S:$S,0)),"") | G12: =IFERROR(INDEX('Шкалы'!$M:$M,MATCH($B$4&"|"&"План"&"|"&$A12&"|"&5&"|"&6,'Шкалы'!$S:$S,0)),"") | W12: КОМПО North America Inc
W13: LUCKY & S CO, Сербия
A14: ОБОРУДОВАНИЕ — шкала скидок | W14: Сейитлиев Мердан Иламанович, Туркменистан
A15: Показатель | B15: =IFERROR(INDEX('Шкалы'!$I:$I,MATCH($B$4&"|"&"Шкала"&"|"&"Оборудование"&"|"&1,'Шкалы'!$R:$R,0)),"") -> до 75 | C15: =IFERROR(INDEX('Шкалы'!$I:$I,MATCH($B$4&"|"&"Шкала"&"|"&"Оборудование"&"|"&2,'Шкалы'!$R:$R,0)),"") -> 75-114 | D15: =IFERROR(INDEX('Шкалы'!$I:$I,MATCH($B$4&"|"&"Шкала"&"|"&"Оборудование"&"|"&3,'Шкалы'!$R:$R,0)),"") -> 115-149 | E15: =IFERROR(INDEX('Шкалы'!$I:$I,MATCH($B$4&"|"&"Шкала"&"|"&"Оборудование"&"|"&4,'Шкалы'!$R:$R,0)),"") -> 150-189 | F15: =IFERROR(INDEX('Шкалы'!$I:$I,MATCH($B$4&"|"&"Шкала"&"|"&"Оборудование"&"|"&5,'Шкалы'!$R:$R,0)),"") -> 190-224 | G15: =IFERROR(INDEX('Шкалы'!$I:$I,MATCH($B$4&"|"&"Шкала"&"|"&"Оборудование"&"|"&6,'Шкалы'!$R:$R,0)),"") -> 225 и более | W15: Ingreda, Молдова
A16: =IFERROR(INDEX('Шкалы'!$F:$F,MATCH($B$4&"|"&"Шкала"&"|"&"Оборудование"&"|"&1,'Шкалы'!$Q:$Q,0)),"") -> 1 Базовое вознаграждение за Дилерский договор | B16: =IFERROR(INDEX('Шкалы'!$M:$M,MATCH($B$4&"|"&"Шкала"&"|"&"Оборудование"&"|"&1&"|"&1,'Шкалы'!$S:$S,0)),"") -> 0.06 | C16: =IFERROR(INDEX('Шкалы'!$M:$M,MATCH($B$4&"|"&"Шкала"&"|"&"Оборудование"&"|"&1&"|"&2,'Шкалы'!$S:$S,0)),"") -> 0.06 | D16: =IFERROR(INDEX('Шкалы'!$M:$M,MATCH($B$4&"|"&"Шкала"&"|"&"Оборудование"&"|"&1&"|"&3,'Шкалы'!$S:$S,0)),"") -> 0.06 | E16: =IFERROR(INDEX('Шкалы'!$M:$M,MATCH($B$4&"|"&"Шкала"&"|"&"Оборудование"&"|"&1&"|"&4,'Шкалы'!$S:$S,0)),"") -> 0.06 | F16: =IFERROR(INDEX('Шкалы'!$M:$M,MATCH($B$4&"|"&"Шкала"&"|"&"Оборудование"&"|"&1&"|"&5,'Шкалы'!$S:$S,0)),"") -> 0.06 | G16: =IFERROR(INDEX('Шкалы'!$M:$M,MATCH($B$4&"|"&"Шкала"&"|"&"Оборудование"&"|"&1&"|"&6,'Шкалы'!$S:$S,0)),"") -> 0.06 | W16: CLIPSOMAC, Алжир
A17: =IFERROR(INDEX('Шкалы'!$F:$F,MATCH($B$4&"|"&"Шкала"&"|"&"Оборудование"&"|"&2,'Шкалы'!$Q:$Q,0)),"") -> 2.1.1. Сервисный центр | B17: =IFERROR(INDEX('Шкалы'!$M:$M,MATCH($B$4&"|"&"Шкала"&"|"&"Оборудование"&"|"&2&"|"&1,'Шкалы'!$S:$S,0)),"") -> 0.06 | C17: =IFERROR(INDEX('Шкалы'!$M:$M,MATCH($B$4&"|"&"Шкала"&"|"&"Оборудование"&"|"&2&"|"&2,'Шкалы'!$S:$S,0)),"") -> 0.06 | D17: =IFERROR(INDEX('Шкалы'!$M:$M,MATCH($B$4&"|"&"Шкала"&"|"&"Оборудование"&"|"&2&"|"&3,'Шкалы'!$S:$S,0)),"") -> 0.06 | E17: =IFERROR(INDEX('Шкалы'!$M:$M,MATCH($B$4&"|"&"Шкала"&"|"&"Оборудование"&"|"&2&"|"&4,'Шкалы'!$S:$S,0)),"") -> 0.06 | F17: =IFERROR(INDEX('Шкалы'!$M:$M,MATCH($B$4&"|"&"Шкала"&"|"&"Оборудование"&"|"&2&"|"&5,'Шкалы'!$S:$S,0)),"") -> 0.06 | G17: =IFERROR(INDEX('Шкалы'!$M:$M,MATCH($B$4&"|"&"Шкала"&"|"&"Оборудование"&"|"&2&"|"&6,'Шкалы'!$S:$S,0)),"") -> 0.06 | W17: Tida Tech, Таиланд
A18: =IFERROR(INDEX('Шкалы'!$F:$F,MATCH($B$4&"|"&"Шкала"&"|"&"Оборудование"&"|"&3,'Шкалы'!$Q:$Q,0)),"") -> 2.1.2. Сервисный центр - гарантийное обслуживание | B18: =IFERROR(INDEX('Шкалы'!$M:$M,MATCH($B$4&"|"&"Шкала"&"|"&"Оборудование"&"|"&3&"|"&1,'Шкалы'!$S:$S,0)),"") -> 0.01 | C18: =IFERROR(INDEX('Шкалы'!$M:$M,MATCH($B$4&"|"&"Шкала"&"|"&"Оборудование"&"|"&3&"|"&2,'Шкалы'!$S:$S,0)),"") -> 0.01 | D18: =IFERROR(INDEX('Шкалы'!$M:$M,MATCH($B$4&"|"&"Шкала"&"|"&"Оборудование"&"|"&3&"|"&3,'Шкалы'!$S:$S,0)),"") -> 0.01 | E18: =IFERROR(INDEX('Шкалы'!$M:$M,MATCH($B$4&"|"&"Шкала"&"|"&"Оборудование"&"|"&3&"|"&4,'Шкалы'!$S:$S,0)),"") -> 0.01 | F18: =IFERROR(INDEX('Шкалы'!$M:$M,MATCH($B$4&"|"&"Шкала"&"|"&"Оборудование"&"|"&3&"|"&5,'Шкалы'!$S:$S,0)),"") -> 0.01 | G18: =IFERROR(INDEX('Шкалы'!$M:$M,MATCH($B$4&"|"&"Шкала"&"|"&"Оборудование"&"|"&3&"|"&6,'Шкалы'!$S:$S,0)),"") -> 0.01 | W18: Ari Makina, Турция
A19: =IFERROR(INDEX('Шкалы'!$F:$F,MATCH($B$4&"|"&"Шкала"&"|"&"Оборудование"&"|"&4,'Шкалы'!$Q:$Q,0)),"") -> 2.3 Наличие минимальных складских остатков по оборудованию | B19: =IFERROR(INDEX('Шкалы'!$M:$M,MATCH($B$4&"|"&"Шкала"&"|"&"Оборудование"&"|"&4&"|"&1,'Шкалы'!$S:$S,0)),"") -> 0.01 | C19: =IFERROR(INDEX('Шкалы'!$M:$M,MATCH($B$4&"|"&"Шкала"&"|"&"Оборудование"&"|"&4&"|"&2,'Шкалы'!$S:$S,0)),"") -> 0.01 | D19: =IFERROR(INDEX('Шкалы'!$M:$M,MATCH($B$4&"|"&"Шкала"&"|"&"Оборудование"&"|"&4&"|"&3,'Шкалы'!$S:$S,0)),"") -> 0.01 | E19: =IFERROR(INDEX('Шкалы'!$M:$M,MATCH($B$4&"|"&"Шкала"&"|"&"Оборудование"&"|"&4&"|"&4,'Шкалы'!$S:$S,0)),"") -> 0.01 | F19: =IFERROR(INDEX('Шкалы'!$M:$M,MATCH($B$4&"|"&"Шкала"&"|"&"Оборудование"&"|"&4&"|"&5,'Шкалы'!$S:$S,0)),"") -> 0.01 | G19: =IFERROR(INDEX('Шкалы'!$M:$M,MATCH($B$4&"|"&"Шкала"&"|"&"Оборудование"&"|"&4&"|"&6,'Шкалы'!$S:$S,0)),"") -> 0.01 | W19: Кабири Хучанд ООО, Таджикистан
A20: =IFERROR(INDEX('Шкалы'!$F:$F,MATCH($B$4&"|"&"Шкала"&"|"&"Оборудование"&"|"&5,'Шкалы'!$Q:$Q,0)),"") -> 3 Объем закупок МП | B20: =IFERROR(INDEX('Шкалы'!$M:$M,MATCH($B$4&"|"&"Шкала"&"|"&"Оборудование"&"|"&5&"|"&1,'Шкалы'!$S:$S,0)),"") -> 0 | C20: =IFERROR(INDEX('Шкалы'!$M:$M,MATCH($B$4&"|"&"Шкала"&"|"&"Оборудование"&"|"&5&"|"&2,'Шкалы'!$S:$S,0)),"") -> 0.01 | D20: =IFERROR(INDEX('Шкалы'!$M:$M,MATCH($B$4&"|"&"Шкала"&"|"&"Оборудование"&"|"&5&"|"&3,'Шкалы'!$S:$S,0)),"") -> 0.02 | E20: =IFERROR(INDEX('Шкалы'!$M:$M,MATCH($B$4&"|"&"Шкала"&"|"&"Оборудование"&"|"&5&"|"&4,'Шкалы'!$S:$S,0)),"") -> 0.03 | F20: =IFERROR(INDEX('Шкалы'!$M:$M,MATCH($B$4&"|"&"Шкала"&"|"&"Оборудование"&"|"&5&"|"&5,'Шкалы'!$S:$S,0)),"") -> 0.04 | G20: =IFERROR(INDEX('Шкалы'!$M:$M,MATCH($B$4&"|"&"Шкала"&"|"&"Оборудование"&"|"&5&"|"&6,'Шкалы'!$S:$S,0)),"") -> 0.05 | W20: Flexo Food , Грузия
A21: =IFERROR(INDEX('Шкалы'!$F:$F,MATCH($B$4&"|"&"Шкала"&"|"&"Оборудование"&"|"&6,'Шкалы'!$Q:$Q,0)),"") -> ИТОГО по МП: | B21: =IFERROR(INDEX('Шкалы'!$M:$M,MATCH($B$4&"|"&"Шкала"&"|"&"Оборудование"&"|"&6&"|"&1,'Шкалы'!$S:$S,0)),"") -> 0.14 | C21: =IFERROR(INDEX('Шкалы'!$M:$M,MATCH($B$4&"|"&"Шкала"&"|"&"Оборудование"&"|"&6&"|"&2,'Шкалы'!$S:$S,0)),"") -> 0.15 | D21: =IFERROR(INDEX('Шкалы'!$M:$M,MATCH($B$4&"|"&"Шкала"&"|"&"Оборудование"&"|"&6&"|"&3,'Шкалы'!$S:$S,0)),"") -> 0.16 | E21: =IFERROR(INDEX('Шкалы'!$M:$M,MATCH($B$4&"|"&"Шкала"&"|"&"Оборудование"&"|"&6&"|"&4,'Шкалы'!$S:$S,0)),"") -> 0.17 | F21: =IFERROR(INDEX('Шкалы'!$M:$M,MATCH($B$4&"|"&"Шкала"&"|"&"Оборудование"&"|"&6&"|"&5,'Шкалы'!$S:$S,0)),"") -> 0.18 | G21: =IFERROR(INDEX('Шкалы'!$M:$M,MATCH($B$4&"|"&"Шкала"&"|"&"Оборудование"&"|"&6&"|"&6,'Шкалы'!$S:$S,0)),"") -> 0.19 | W21: Гинап, Армения
A22: =IFERROR(INDEX('Шкалы'!$F:$F,MATCH($B$4&"|"&"Шкала"&"|"&"Оборудование"&"|"&7,'Шкалы'!$Q:$Q,0)),"") -> Наличие минимальных складских остатков по РМ (синхронизация отчета по остаткам с 1С КОМПО) | B22: =IFERROR(INDEX('Шкалы'!$M:$M,MATCH($B$4&"|"&"Шкала"&"|"&"Оборудование"&"|"&7&"|"&1,'Шкалы'!$S:$S,0)),"") -> 0.01 | C22: =IFERROR(INDEX('Шкалы'!$M:$M,MATCH($B$4&"|"&"Шкала"&"|"&"Оборудование"&"|"&7&"|"&2,'Шкалы'!$S:$S,0)),"") -> 0.01 | D22: =IFERROR(INDEX('Шкалы'!$M:$M,MATCH($B$4&"|"&"Шкала"&"|"&"Оборудование"&"|"&7&"|"&3,'Шкалы'!$S:$S,0)),"") -> 0.01 | E22: =IFERROR(INDEX('Шкалы'!$M:$M,MATCH($B$4&"|"&"Шкала"&"|"&"Оборудование"&"|"&7&"|"&4,'Шкалы'!$S:$S,0)),"") -> 0.01 | F22: =IFERROR(INDEX('Шкалы'!$M:$M,MATCH($B$4&"|"&"Шкала"&"|"&"Оборудование"&"|"&7&"|"&5,'Шкалы'!$S:$S,0)),"") -> 0.01 | G22: =IFERROR(INDEX('Шкалы'!$M:$M,MATCH($B$4&"|"&"Шкала"&"|"&"Оборудование"&"|"&7&"|"&6,'Шкалы'!$S:$S,0)),"") -> 0.01
A23: =IFERROR(INDEX('Шкалы'!$F:$F,MATCH($B$4&"|"&"Шкала"&"|"&"Оборудование"&"|"&8,'Шкалы'!$Q:$Q,0)),"") -> Объем закупок РМ | B23: =IFERROR(INDEX('Шкалы'!$M:$M,MATCH($B$4&"|"&"Шкала"&"|"&"Оборудование"&"|"&8&"|"&1,'Шкалы'!$S:$S,0)),"") -> 0 | C23: =IFERROR(INDEX('Шкалы'!$M:$M,MATCH($B$4&"|"&"Шкала"&"|"&"Оборудование"&"|"&8&"|"&2,'Шкалы'!$S:$S,0)),"") -> 0.01 | D23: =IFERROR(INDEX('Шкалы'!$M:$M,MATCH($B$4&"|"&"Шкала"&"|"&"Оборудование"&"|"&8&"|"&3,'Шкалы'!$S:$S,0)),"") -> 0.02 | E23: =IFERROR(INDEX('Шкалы'!$M:$M,MATCH($B$4&"|"&"Шкала"&"|"&"Оборудование"&"|"&8&"|"&4,'Шкалы'!$S:$S,0)),"") -> 0.03 | F23: =IFERROR(INDEX('Шкалы'!$M:$M,MATCH($B$4&"|"&"Шкала"&"|"&"Оборудование"&"|"&8&"|"&5,'Шкалы'!$S:$S,0)),"") -> 0.04 | G23: =IFERROR(INDEX('Шкалы'!$M:$M,MATCH($B$4&"|"&"Шкала"&"|"&"Оборудование"&"|"&8&"|"&6,'Шкалы'!$S:$S,0)),"") -> 0.05
A24: =IFERROR(INDEX('Шкалы'!$F:$F,MATCH($B$4&"|"&"Шкала"&"|"&"Оборудование"&"|"&9,'Шкалы'!$Q:$Q,0)),"") | B24: =IFERROR(INDEX('Шкалы'!$M:$M,MATCH($B$4&"|"&"Шкала"&"|"&"Оборудование"&"|"&9&"|"&1,'Шкалы'!$S:$S,0)),"") | C24: =IFERROR(INDEX('Шкалы'!$M:$M,MATCH($B$4&"|"&"Шкала"&"|"&"Оборудование"&"|"&9&"|"&2,'Шкалы'!$S:$S,0)),"") | D24: =IFERROR(INDEX('Шкалы'!$M:$M,MATCH($B$4&"|"&"Шкала"&"|"&"Оборудование"&"|"&9&"|"&3,'Шкалы'!$S:$S,0)),"") | E24: =IFERROR(INDEX('Шкалы'!$M:$M,MATCH($B$4&"|"&"Шкала"&"|"&"Оборудование"&"|"&9&"|"&4,'Шкалы'!$S:$S,0)),"") | F24: =IFERROR(INDEX('Шкалы'!$M:$M,MATCH($B$4&"|"&"Шкала"&"|"&"Оборудование"&"|"&9&"|"&5,'Шкалы'!$S:$S,0)),"") | G24: =IFERROR(INDEX('Шкалы'!$M:$M,MATCH($B$4&"|"&"Шкала"&"|"&"Оборудование"&"|"&9&"|"&6,'Шкалы'!$S:$S,0)),"")
A26: РАСХОДНЫЕ МАТЕРИАЛЫ — шкала скидок
A27: Показатель | B27: =IFERROR(INDEX('Шкалы'!$I:$I,MATCH($B$4&"|"&"Шкала"&"|"&"Расходные материалы"&"|"&1,'Шкалы'!$R:$R,0)),"") -> до 75 | C27: =IFERROR(INDEX('Шкалы'!$I:$I,MATCH($B$4&"|"&"Шкала"&"|"&"Расходные материалы"&"|"&2,'Шкалы'!$R:$R,0)),"") -> 75-115 | D27: =IFERROR(INDEX('Шкалы'!$I:$I,MATCH($B$4&"|"&"Шкала"&"|"&"Расходные материалы"&"|"&3,'Шкалы'!$R:$R,0)),"") -> 115-150 | E27: =IFERROR(INDEX('Шкалы'!$I:$I,MATCH($B$4&"|"&"Шкала"&"|"&"Расходные материалы"&"|"&4,'Шкалы'!$R:$R,0)),"") -> 150-190 | F27: =IFERROR(INDEX('Шкалы'!$I:$I,MATCH($B$4&"|"&"Шкала"&"|"&"Расходные материалы"&"|"&5,'Шкалы'!$R:$R,0)),"") -> 190-225 | G27: =IFERROR(INDEX('Шкалы'!$I:$I,MATCH($B$4&"|"&"Шкала"&"|"&"Расходные материалы"&"|"&6,'Шкалы'!$R:$R,0)),"") -> 225 и более
A28: =IFERROR(INDEX('Шкалы'!$F:$F,MATCH($B$4&"|"&"Шкала"&"|"&"Расходные материалы"&"|"&1,'Шкалы'!$Q:$Q,0)),"") -> Наличие минимальных складских остатков по РМ (синхронизация отчета по остаткам с 1С КОМПО) | B28: =IFERROR(INDEX('Шкалы'!$M:$M,MATCH($B$4&"|"&"Шкала"&"|"&"Расходные материалы"&"|"&1&"|"&1,'Шкалы'!$S:$S,0)),"") -> 0.01 | C28: =IFERROR(INDEX('Шкалы'!$M:$M,MATCH($B$4&"|"&"Шкала"&"|"&"Расходные материалы"&"|"&1&"|"&2,'Шкалы'!$S:$S,0)),"") -> 0.01 | D28: =IFERROR(INDEX('Шкалы'!$M:$M,MATCH($B$4&"|"&"Шкала"&"|"&"Расходные материалы"&"|"&1&"|"&3,'Шкалы'!$S:$S,0)),"") -> 0.01 | E28: =IFERROR(INDEX('Шкалы'!$M:$M,MATCH($B$4&"|"&"Шкала"&"|"&"Расходные материалы"&"|"&1&"|"&4,'Шкалы'!$S:$S,0)),"") -> 0.01 | F28: =IFERROR(INDEX('Шкалы'!$M:$M,MATCH($B$4&"|"&"Шкала"&"|"&"Расходные материалы"&"|"&1&"|"&5,'Шкалы'!$S:$S,0)),"") -> 0.01 | G28: =IFERROR(INDEX('Шкалы'!$M:$M,MATCH($B$4&"|"&"Шкала"&"|"&"Расходные материалы"&"|"&1&"|"&6,'Шкалы'!$S:$S,0)),"") -> 0.01
A29: =IFERROR(INDEX('Шкалы'!$F:$F,MATCH($B$4&"|"&"Шкала"&"|"&"Расходные материалы"&"|"&2,'Шкалы'!$Q:$Q,0)),"") -> Объем закупок РМ | B29: =IFERROR(INDEX('Шкалы'!$M:$M,MATCH($B$4&"|"&"Шкала"&"|"&"Расходные материалы"&"|"&2&"|"&1,'Шкалы'!$S:$S,0)),"") -> 0 | C29: =IFERROR(INDEX('Шкалы'!$M:$M,MATCH($B$4&"|"&"Шкала"&"|"&"Расходные материалы"&"|"&2&"|"&2,'Шкалы'!$S:$S,0)),"") -> 0.01 | D29: =IFERROR(INDEX('Шкалы'!$M:$M,MATCH($B$4&"|"&"Шкала"&"|"&"Расходные материалы"&"|"&2&"|"&3,'Шкалы'!$S:$S,0)),"") -> 0.02 | E29: =IFERROR(INDEX('Шкалы'!$M:$M,MATCH($B$4&"|"&"Шкала"&"|"&"Расходные материалы"&"|"&2&"|"&4,'Шкалы'!$S:$S,0)),"") -> 0.03 | F29: =IFERROR(INDEX('Шкалы'!$M:$M,MATCH($B$4&"|"&"Шкала"&"|"&"Расходные материалы"&"|"&2&"|"&5,'Шкалы'!$S:$S,0)),"") -> 0.04 | G29: =IFERROR(INDEX('Шкалы'!$M:$M,MATCH($B$4&"|"&"Шкала"&"|"&"Расходные материалы"&"|"&2&"|"&6,'Шкалы'!$S:$S,0)),"") -> 0.05
A30: =IFERROR(INDEX('Шкалы'!$F:$F,MATCH($B$4&"|"&"Шкала"&"|"&"Расходные материалы"&"|"&3,'Шкалы'!$Q:$Q,0)),"") | B30: =IFERROR(INDEX('Шкалы'!$M:$M,MATCH($B$4&"|"&"Шкала"&"|"&"Расходные материалы"&"|"&3&"|"&1,'Шкалы'!$S:$S,0)),"") | C30: =IFERROR(INDEX('Шкалы'!$M:$M,MATCH($B$4&"|"&"Шкала"&"|"&"Расходные материалы"&"|"&3&"|"&2,'Шкалы'!$S:$S,0)),"") | D30: =IFERROR(INDEX('Шкалы'!$M:$M,MATCH($B$4&"|"&"Шкала"&"|"&"Расходные материалы"&"|"&3&"|"&3,'Шкалы'!$S:$S,0)),"") | E30: =IFERROR(INDEX('Шкалы'!$M:$M,MATCH($B$4&"|"&"Шкала"&"|"&"Расходные материалы"&"|"&3&"|"&4,'Шкалы'!$S:$S,0)),"") | F30: =IFERROR(INDEX('Шкалы'!$M:$M,MATCH($B$4&"|"&"Шкала"&"|"&"Расходные материалы"&"|"&3&"|"&5,'Шкалы'!$S:$S,0)),"") | G30: =IFERROR(INDEX('Шкалы'!$M:$M,MATCH($B$4&"|"&"Шкала"&"|"&"Расходные материалы"&"|"&3&"|"&6,'Шкалы'!$S:$S,0)),"")
A31: =IFERROR(INDEX('Шкалы'!$F:$F,MATCH($B$4&"|"&"Шкала"&"|"&"Расходные материалы"&"|"&4,'Шкалы'!$Q:$Q,0)),"") | B31: =IFERROR(INDEX('Шкалы'!$M:$M,MATCH($B$4&"|"&"Шкала"&"|"&"Расходные материалы"&"|"&4&"|"&1,'Шкалы'!$S:$S,0)),"") | C31: =IFERROR(INDEX('Шкалы'!$M:$M,MATCH($B$4&"|"&"Шкала"&"|"&"Расходные материалы"&"|"&4&"|"&2,'Шкалы'!$S:$S,0)),"") | D31: =IFERROR(INDEX('Шкалы'!$M:$M,MATCH($B$4&"|"&"Шкала"&"|"&"Расходные материалы"&"|"&4&"|"&3,'Шкалы'!$S:$S,0)),"") | E31: =IFERROR(INDEX('Шкалы'!$M:$M,MATCH($B$4&"|"&"Шкала"&"|"&"Расходные материалы"&"|"&4&"|"&4,'Шкалы'!$S:$S,0)),"") | F31: =IFERROR(INDEX('Шкалы'!$M:$M,MATCH($B$4&"|"&"Шкала"&"|"&"Расходные материалы"&"|"&4&"|"&5,'Шкалы'!$S:$S,0)),"") | G31: =IFERROR(INDEX('Шкалы'!$M:$M,MATCH($B$4&"|"&"Шкала"&"|"&"Расходные материалы"&"|"&4&"|"&6,'Шкалы'!$S:$S,0)),"")
A33: СЕРВИС (ЗЧ) — шкала скидок
A34: Показатель | B34: =IFERROR(INDEX('Шкалы'!$I:$I,MATCH($B$4&"|"&"Шкала"&"|"&"Сервис (ЗЧ)"&"|"&1,'Шкалы'!$R:$R,0)),"") -> 0–500 | C34: =IFERROR(INDEX('Шкалы'!$I:$I,MATCH($B$4&"|"&"Шкала"&"|"&"Сервис (ЗЧ)"&"|"&2,'Шкалы'!$R:$R,0)),"") -> 501–1000 | D34: =IFERROR(INDEX('Шкалы'!$I:$I,MATCH($B$4&"|"&"Шкала"&"|"&"Сервис (ЗЧ)"&"|"&3,'Шкалы'!$R:$R,0)),"") -> 1001–1800 | E34: =IFERROR(INDEX('Шкалы'!$I:$I,MATCH($B$4&"|"&"Шкала"&"|"&"Сервис (ЗЧ)"&"|"&4,'Шкалы'!$R:$R,0)),"") -> 1801–2400 | F34: =IFERROR(INDEX('Шкалы'!$I:$I,MATCH($B$4&"|"&"Шкала"&"|"&"Сервис (ЗЧ)"&"|"&5,'Шкалы'!$R:$R,0)),"") -> 2401–3000 | G34: =IFERROR(INDEX('Шкалы'!$I:$I,MATCH($B$4&"|"&"Шкала"&"|"&"Сервис (ЗЧ)"&"|"&6,'Шкалы'!$R:$R,0)),"") -> 3001+ | H34: =IFERROR(INDEX('Шкалы'!$I:$I,MATCH($B$4&"|"&"Шкала"&"|"&"Сервис (ЗЧ)"&"|"&7,'Шкалы'!$R:$R,0)),"") | I34: =IFERROR(INDEX('Шкалы'!$I:$I,MATCH($B$4&"|"&"Шкала"&"|"&"Сервис (ЗЧ)"&"|"&8,'Шкалы'!$R:$R,0)),"") | J34: =IFERROR(INDEX('Шкалы'!$I:$I,MATCH($B$4&"|"&"Шкала"&"|"&"Сервис (ЗЧ)"&"|"&9,'Шкалы'!$R:$R,0)),"") | K34: =IFERROR(INDEX('Шкалы'!$I:$I,MATCH($B$4&"|"&"Шкала"&"|"&"Сервис (ЗЧ)"&"|"&10,'Шкалы'!$R:$R,0)),"") | L34: =IFERROR(INDEX('Шкалы'!$I:$I,MATCH($B$4&"|"&"Шкала"&"|"&"Сервис (ЗЧ)"&"|"&11,'Шкалы'!$R:$R,0)),"") | M34: =IFERROR(INDEX('Шкалы'!$I:$I,MATCH($B$4&"|"&"Шкала"&"|"&"Сервис (ЗЧ)"&"|"&12,'Шкалы'!$R:$R,0)),"")
A35: =IFERROR(INDEX('Шкалы'!$F:$F,MATCH($B$4&"|"&"Шкала"&"|"&"Сервис (ЗЧ)"&"|"&1,'Шкалы'!$Q:$Q,0)),"") -> Скидка по сервису | B35: =IFERROR(INDEX('Шкалы'!$M:$M,MATCH($B$4&"|"&"Шкала"&"|"&"Сервис (ЗЧ)"&"|"&1&"|"&1,'Шкалы'!$S:$S,0)),"") -> 0.19 | C35: =IFERROR(INDEX('Шкалы'!$M:$M,MATCH($B$4&"|"&"Шкала"&"|"&"Сервис (ЗЧ)"&"|"&1&"|"&2,'Шкалы'!$S:$S,0)),"") -> 0.21 | D35: =IFERROR(INDEX('Шкалы'!$M:$M,MATCH($B$4&"|"&"Шкала"&"|"&"Сервис (ЗЧ)"&"|"&1&"|"&3,'Шкалы'!$S:$S,0)),"") -> 0.23 | E35: =IFERROR(INDEX('Шкалы'!$M:$M,MATCH($B$4&"|"&"Шкала"&"|"&"Сервис (ЗЧ)"&"|"&1&"|"&4,'Шкалы'!$S:$S,0)),"") -> 0.25 | F35: =IFERROR(INDEX('Шкалы'!$M:$M,MATCH($B$4&"|"&"Шкала"&"|"&"Сервис (ЗЧ)"&"|"&1&"|"&5,'Шкалы'!$S:$S,0)),"") -> 0.27 | G35: =IFERROR(INDEX('Шкалы'!$M:$M,MATCH($B$4&"|"&"Шкала"&"|"&"Сервис (ЗЧ)"&"|"&1&"|"&6,'Шкалы'!$S:$S,0)),"") -> 0.3 | H35: =IFERROR(INDEX('Шкалы'!$M:$M,MATCH($B$4&"|"&"Шкала"&"|"&"Сервис (ЗЧ)"&"|"&1&"|"&7,'Шкалы'!$S:$S,0)),"") | I35: =IFERROR(INDEX('Шкалы'!$M:$M,MATCH($B$4&"|"&"Шкала"&"|"&"Сервис (ЗЧ)"&"|"&1&"|"&8,'Шкалы'!$S:$S,0)),"") | J35: =IFERROR(INDEX('Шкалы'!$M:$M,MATCH($B$4&"|"&"Шкала"&"|"&"Сервис (ЗЧ)"&"|"&1&"|"&9,'Шкалы'!$S:$S,0)),"") | K35: =IFERROR(INDEX('Шкалы'!$M:$M,MATCH($B$4&"|"&"Шкала"&"|"&"Сервис (ЗЧ)"&"|"&1&"|"&10,'Шкалы'!$S:$S,0)),"") | L35: =IFERROR(INDEX('Шкалы'!$M:$M,MATCH($B$4&"|"&"Шкала"&"|"&"Сервис (ЗЧ)"&"|"&1&"|"&11,'Шкалы'!$S:$S,0)),"") | M35: =IFERROR(INDEX('Шкалы'!$M:$M,MATCH($B$4&"|"&"Шкала"&"|"&"Сервис (ЗЧ)"&"|"&1&"|"&12,'Шкалы'!$S:$S,0)),"")
A37: СРАВНЕНИЕ ДИЛЕРОВ — строка ИТОГО по оборудованию
A38: Дилер | B38: =B15 -> до 75 | C38: =C15 -> 75-114 | D38: =D15 -> 115-149 | E38: =E15 -> 150-189 | F38: =F15 -> 190-224 | G38: =G15 -> 225 и более | H38: Тип
A39: =$W$4 -> КОМПО Технолоджис | B39: =IFERROR(INDEX('Шкалы'!$M:$M,MATCH($A39&"|"&"Шкала"&"|"&"Оборудование"&"|"&1,'Шкалы'!$U:$U,0)),"") -> 0.14 | C39: =IFERROR(INDEX('Шкалы'!$M:$M,MATCH($A39&"|"&"Шкала"&"|"&"Оборудование"&"|"&2,'Шкалы'!$U:$U,0)),"") -> 0.15 | D39: =IFERROR(INDEX('Шкалы'!$M:$M,MATCH($A39&"|"&"Шкала"&"|"&"Оборудование"&"|"&3,'Шкалы'!$U:$U,0)),"") -> 0.16 | E39: =IFERROR(INDEX('Шкалы'!$M:$M,MATCH($A39&"|"&"Шкала"&"|"&"Оборудование"&"|"&4,'Шкалы'!$U:$U,0)),"") -> 0.17 | F39: =IFERROR(INDEX('Шкалы'!$M:$M,MATCH($A39&"|"&"Шкала"&"|"&"Оборудование"&"|"&5,'Шкалы'!$U:$U,0)),"") -> 0.18 | G39: =IFERROR(INDEX('Шкалы'!$M:$M,MATCH($A39&"|"&"Шкала"&"|"&"Оборудование"&"|"&6,'Шкалы'!$U:$U,0)),"") -> 0.19 | H39: =IFERROR(INDEX('Шкалы'!$B:$B,MATCH($A39,'Шкалы'!$A:$A,0)),"") -> РФ
A40: =$W$5 -> НоваПак | B40: =IFERROR(INDEX('Шкалы'!$M:$M,MATCH($A40&"|"&"Шкала"&"|"&"Оборудование"&"|"&1,'Шкалы'!$U:$U,0)),"") -> 0.14 | C40: =IFERROR(INDEX('Шкалы'!$M:$M,MATCH($A40&"|"&"Шкала"&"|"&"Оборудование"&"|"&2,'Шкалы'!$U:$U,0)),"") -> 0.15 | D40: =IFERROR(INDEX('Шкалы'!$M:$M,MATCH($A40&"|"&"Шкала"&"|"&"Оборудование"&"|"&3,'Шкалы'!$U:$U,0)),"") -> 0.16 | E40: =IFERROR(INDEX('Шкалы'!$M:$M,MATCH($A40&"|"&"Шкала"&"|"&"Оборудование"&"|"&4,'Шкалы'!$U:$U,0)),"") -> 0.17 | F40: =IFERROR(INDEX('Шкалы'!$M:$M,MATCH($A40&"|"&"Шкала"&"|"&"Оборудование"&"|"&5,'Шкалы'!$U:$U,0)),"") -> 0.18 | G40: =IFERROR(INDEX('Шкалы'!$M:$M,MATCH($A40&"|"&"Шкала"&"|"&"Оборудование"&"|"&6,'Шкалы'!$U:$U,0)),"") -> 0.19 | H40: =IFERROR(INDEX('Шкалы'!$B:$B,MATCH($A40,'Шкалы'!$A:$A,0)),"") -> РФ
A41: =$W$6 -> КСП (КОМПО-СП) | B41: =IFERROR(INDEX('Шкалы'!$M:$M,MATCH($A41&"|"&"Шкала"&"|"&"Оборудование"&"|"&1,'Шкалы'!$U:$U,0)),"") -> 0.14 | C41: =IFERROR(INDEX('Шкалы'!$M:$M,MATCH($A41&"|"&"Шкала"&"|"&"Оборудование"&"|"&2,'Шкалы'!$U:$U,0)),"") -> 0.15 | D41: =IFERROR(INDEX('Шкалы'!$M:$M,MATCH($A41&"|"&"Шкала"&"|"&"Оборудование"&"|"&3,'Шкалы'!$U:$U,0)),"") -> 0.16 | E41: =IFERROR(INDEX('Шкалы'!$M:$M,MATCH($A41&"|"&"Шкала"&"|"&"Оборудование"&"|"&4,'Шкалы'!$U:$U,0)),"") -> 0.17 | F41: =IFERROR(INDEX('Шкалы'!$M:$M,MATCH($A41&"|"&"Шкала"&"|"&"Оборудование"&"|"&5,'Шкалы'!$U:$U,0)),"") -> 0.18 | G41: =IFERROR(INDEX('Шкалы'!$M:$M,MATCH($A41&"|"&"Шкала"&"|"&"Оборудование"&"|"&6,'Шкалы'!$U:$U,0)),"") -> 0.19 | H41: =IFERROR(INDEX('Шкалы'!$B:$B,MATCH($A41,'Шкалы'!$A:$A,0)),"") -> РФ
A42: =$W$7 -> Богатовъ Торговый Дом, Челябинск | B42: =IFERROR(INDEX('Шкалы'!$M:$M,MATCH($A42&"|"&"Шкала"&"|"&"Оборудование"&"|"&1,'Шкалы'!$U:$U,0)),"") -> 0.14 | C42: =IFERROR(INDEX('Шкалы'!$M:$M,MATCH($A42&"|"&"Шкала"&"|"&"Оборудование"&"|"&2,'Шкалы'!$U:$U,0)),"") -> 0.15 | D42: =IFERROR(INDEX('Шкалы'!$M:$M,MATCH($A42&"|"&"Шкала"&"|"&"Оборудование"&"|"&3,'Шкалы'!$U:$U,0)),"") -> 0.16 | E42: =IFERROR(INDEX('Шкалы'!$M:$M,MATCH($A42&"|"&"Шкала"&"|"&"Оборудование"&"|"&4,'Шкалы'!$U:$U,0)),"") -> 0.17 | F42: =IFERROR(INDEX('Шкалы'!$M:$M,MATCH($A42&"|"&"Шкала"&"|"&"Оборудование"&"|"&5,'Шкалы'!$U:$U,0)),"") -> 0.18 | G42: =IFERROR(INDEX('Шкалы'!$M:$M,MATCH($A42&"|"&"Шкала"&"|"&"Оборудование"&"|"&6,'Шкалы'!$U:$U,0)),"") -> 0.19 | H42: =IFERROR(INDEX('Шкалы'!$B:$B,MATCH($A42,'Шкалы'!$A:$A,0)),"") -> РФ
A43: =$W$8 -> ASIAN BUSINESS SOLUTIONS, Узбекистан | B43: =IFERROR(INDEX('Шкалы'!$M:$M,MATCH($A43&"|"&"Шкала"&"|"&"Оборудование"&"|"&1,'Шкалы'!$U:$U,0)),"") -> 0.14 | C43: =IFERROR(INDEX('Шкалы'!$M:$M,MATCH($A43&"|"&"Шкала"&"|"&"Оборудование"&"|"&2,'Шкалы'!$U:$U,0)),"") -> 0.16 | D43: =IFERROR(INDEX('Шкалы'!$M:$M,MATCH($A43&"|"&"Шкала"&"|"&"Оборудование"&"|"&3,'Шкалы'!$U:$U,0)),"") -> 0.17 | E43: =IFERROR(INDEX('Шкалы'!$M:$M,MATCH($A43&"|"&"Шкала"&"|"&"Оборудование"&"|"&4,'Шкалы'!$U:$U,0)),"") -> 0.18 | F43: =IFERROR(INDEX('Шкалы'!$M:$M,MATCH($A43&"|"&"Шкала"&"|"&"Оборудование"&"|"&5,'Шкалы'!$U:$U,0)),"") -> 0.19 | G43: =IFERROR(INDEX('Шкалы'!$M:$M,MATCH($A43&"|"&"Шкала"&"|"&"Оборудование"&"|"&6,'Шкалы'!$U:$U,0)),"") -> 0.2 | H43: =IFERROR(INDEX('Шкалы'!$B:$B,MATCH($A43,'Шкалы'!$A:$A,0)),"") -> Заруб
A44: =$W$9 -> Deling food | B44: =IFERROR(INDEX('Шкалы'!$M:$M,MATCH($A44&"|"&"Шкала"&"|"&"Оборудование"&"|"&1,'Шкалы'!$U:$U,0)),"") -> 0.14 | C44: =IFERROR(INDEX('Шкалы'!$M:$M,MATCH($A44&"|"&"Шкала"&"|"&"Оборудование"&"|"&2,'Шкалы'!$U:$U,0)),"") -> 0.16 | D44: =IFERROR(INDEX('Шкалы'!$M:$M,MATCH($A44&"|"&"Шкала"&"|"&"Оборудование"&"|"&3,'Шкалы'!$U:$U,0)),"") -> 0.17 | E44: =IFERROR(INDEX('Шкалы'!$M:$M,MATCH($A44&"|"&"Шкала"&"|"&"Оборудование"&"|"&4,'Шкалы'!$U:$U,0)),"") -> 0.18 | F44: =IFERROR(INDEX('Шкалы'!$M:$M,MATCH($A44&"|"&"Шкала"&"|"&"Оборудование"&"|"&5,'Шкалы'!$U:$U,0)),"") -> 0.19 | G44: =IFERROR(INDEX('Шкалы'!$M:$M,MATCH($A44&"|"&"Шкала"&"|"&"Оборудование"&"|"&6,'Шкалы'!$U:$U,0)),"") -> 0.2 | H44: =IFERROR(INDEX('Шкалы'!$B:$B,MATCH($A44,'Шкалы'!$A:$A,0)),"") -> Заруб
A45: =$W$10 -> VitLine, Казахстан | B45: =IFERROR(INDEX('Шкалы'!$M:$M,MATCH($A45&"|"&"Шкала"&"|"&"Оборудование"&"|"&1,'Шкалы'!$U:$U,0)),"") -> 0.14 | C45: =IFERROR(INDEX('Шкалы'!$M:$M,MATCH($A45&"|"&"Шкала"&"|"&"Оборудование"&"|"&2,'Шкалы'!$U:$U,0)),"") -> 0.16 | D45: =IFERROR(INDEX('Шкалы'!$M:$M,MATCH($A45&"|"&"Шкала"&"|"&"Оборудование"&"|"&3,'Шкалы'!$U:$U,0)),"") -> 0.17 | E45: =IFERROR(INDEX('Шкалы'!$M:$M,MATCH($A45&"|"&"Шкала"&"|"&"Оборудование"&"|"&4,'Шкалы'!$U:$U,0)),"") -> 0.18 | F45: =IFERROR(INDEX('Шкалы'!$M:$M,MATCH($A45&"|"&"Шкала"&"|"&"Оборудование"&"|"&5,'Шкалы'!$U:$U,0)),"") -> 0.19 | G45: =IFERROR(INDEX('Шкалы'!$M:$M,MATCH($A45&"|"&"Шкала"&"|"&"Оборудование"&"|"&6,'Шкалы'!$U:$U,0)),"") -> 0.2 | H45: =IFERROR(INDEX('Шкалы'!$B:$B,MATCH($A45,'Шкалы'!$A:$A,0)),"") -> Заруб
A46: =$W$11 -> UNIVERSAL MEAT | B46: =IFERROR(INDEX('Шкалы'!$M:$M,MATCH($A46&"|"&"Шкала"&"|"&"Оборудование"&"|"&1,'Шкалы'!$U:$U,0)),"") -> 0.14 | C46: =IFERROR(INDEX('Шкалы'!$M:$M,MATCH($A46&"|"&"Шкала"&"|"&"Оборудование"&"|"&2,'Шкалы'!$U:$U,0)),"") -> 0.16 | D46: =IFERROR(INDEX('Шкалы'!$M:$M,MATCH($A46&"|"&"Шкала"&"|"&"Оборудование"&"|"&3,'Шкалы'!$U:$U,0)),"") -> 0.17 | E46: =IFERROR(INDEX('Шкалы'!$M:$M,MATCH($A46&"|"&"Шкала"&"|"&"Оборудование"&"|"&4,'Шкалы'!$U:$U,0)),"") -> 0.18 | F46: =IFERROR(INDEX('Шкалы'!$M:$M,MATCH($A46&"|"&"Шкала"&"|"&"Оборудование"&"|"&5,'Шкалы'!$U:$U,0)),"") -> 0.19 | G46: =IFERROR(INDEX('Шкалы'!$M:$M,MATCH($A46&"|"&"Шкала"&"|"&"Оборудование"&"|"&6,'Шкалы'!$U:$U,0)),"") -> 0.2 | H46: =IFERROR(INDEX('Шкалы'!$B:$B,MATCH($A46,'Шкалы'!$A:$A,0)),"") -> Заруб
A47: =$W$12 -> КОМПО North America Inc | B47: =IFERROR(INDEX('Шкалы'!$M:$M,MATCH($A47&"|"&"Шкала"&"|"&"Оборудование"&"|"&1,'Шкалы'!$U:$U,0)),"") -> 0.07 | C47: =IFERROR(INDEX('Шкалы'!$M:$M,MATCH($A47&"|"&"Шкала"&"|"&"Оборудование"&"|"&2,'Шкалы'!$U:$U,0)),"") -> 0.16 | D47: =IFERROR(INDEX('Шкалы'!$M:$M,MATCH($A47&"|"&"Шкала"&"|"&"Оборудование"&"|"&3,'Шкалы'!$U:$U,0)),"") -> 0.17 | E47: =IFERROR(INDEX('Шкалы'!$M:$M,MATCH($A47&"|"&"Шкала"&"|"&"Оборудование"&"|"&4,'Шкалы'!$U:$U,0)),"") -> 0.18 | F47: =IFERROR(INDEX('Шкалы'!$M:$M,MATCH($A47&"|"&"Шкала"&"|"&"Оборудование"&"|"&5,'Шкалы'!$U:$U,0)),"") -> 0.19 | G47: =IFERROR(INDEX('Шкалы'!$M:$M,MATCH($A47&"|"&"Шкала"&"|"&"Оборудование"&"|"&6,'Шкалы'!$U:$U,0)),"") -> 0.2 | H47: =IFERROR(INDEX('Шкалы'!$B:$B,MATCH($A47,'Шкалы'!$A:$A,0)),"") -> Заруб
A48: =$W$13 -> LUCKY & S CO, Сербия | B48: =IFERROR(INDEX('Шкалы'!$M:$M,MATCH($A48&"|"&"Шкала"&"|"&"Оборудование"&"|"&1,'Шкалы'!$U:$U,0)),"") -> 0.14 | C48: =IFERROR(INDEX('Шкалы'!$M:$M,MATCH($A48&"|"&"Шкала"&"|"&"Оборудование"&"|"&2,'Шкалы'!$U:$U,0)),"") -> 0.16 | D48: =IFERROR(INDEX('Шкалы'!$M:$M,MATCH($A48&"|"&"Шкала"&"|"&"Оборудование"&"|"&3,'Шкалы'!$U:$U,0)),"") -> 0.17 | E48: =IFERROR(INDEX('Шкалы'!$M:$M,MATCH($A48&"|"&"Шкала"&"|"&"Оборудование"&"|"&4,'Шкалы'!$U:$U,0)),"") -> 0.18 | F48: =IFERROR(INDEX('Шкалы'!$M:$M,MATCH($A48&"|"&"Шкала"&"|"&"Оборудование"&"|"&5,'Шкалы'!$U:$U,0)),"") -> 0.19 | G48: =IFERROR(INDEX('Шкалы'!$M:$M,MATCH($A48&"|"&"Шкала"&"|"&"Оборудование"&"|"&6,'Шкалы'!$U:$U,0)),"") -> 0.2 | H48: =IFERROR(INDEX('Шкалы'!$B:$B,MATCH($A48,'Шкалы'!$A:$A,0)),"") -> Заруб
A49: =$W$14 -> Сейитлиев Мердан Иламанович, Туркменистан | B49: =IFERROR(INDEX('Шкалы'!$M:$M,MATCH($A49&"|"&"Шкала"&"|"&"Оборудование"&"|"&1,'Шкалы'!$U:$U,0)),"") -> 0.14 | C49: =IFERROR(INDEX('Шкалы'!$M:$M,MATCH($A49&"|"&"Шкала"&"|"&"Оборудование"&"|"&2,'Шкалы'!$U:$U,0)),"") -> 0.16 | D49: =IFERROR(INDEX('Шкалы'!$M:$M,MATCH($A49&"|"&"Шкала"&"|"&"Оборудование"&"|"&3,'Шкалы'!$U:$U,0)),"") -> 0.17 | E49: =IFERROR(INDEX('Шкалы'!$M:$M,MATCH($A49&"|"&"Шкала"&"|"&"Оборудование"&"|"&4,'Шкалы'!$U:$U,0)),"") -> 0.18 | F49: =IFERROR(INDEX('Шкалы'!$M:$M,MATCH($A49&"|"&"Шкала"&"|"&"Оборудование"&"|"&5,'Шкалы'!$U:$U,0)),"") -> 0.19 | G49: =IFERROR(INDEX('Шкалы'!$M:$M,MATCH($A49&"|"&"Шкала"&"|"&"Оборудование"&"|"&6,'Шкалы'!$U:$U,0)),"") -> 0.2 | H49: =IFERROR(INDEX('Шкалы'!$B:$B,MATCH($A49,'Шкалы'!$A:$A,0)),"") -> Заруб
A50: =$W$15 -> Ingreda, Молдова | B50: =IFERROR(INDEX('Шкалы'!$M:$M,MATCH($A50&"|"&"Шкала"&"|"&"Оборудование"&"|"&1,'Шкалы'!$U:$U,0)),"") -> 0.14 | C50: =IFERROR(INDEX('Шкалы'!$M:$M,MATCH($A50&"|"&"Шкала"&"|"&"Оборудование"&"|"&2,'Шкалы'!$U:$U,0)),"") -> 0.16 | D50: =IFERROR(INDEX('Шкалы'!$M:$M,MATCH($A50&"|"&"Шкала"&"|"&"Оборудование"&"|"&3,'Шкалы'!$U:$U,0)),"") -> 0.17 | E50: =IFERROR(INDEX('Шкалы'!$M:$M,MATCH($A50&"|"&"Шкала"&"|"&"Оборудование"&"|"&4,'Шкалы'!$U:$U,0)),"") -> 0.18 | F50: =IFERROR(INDEX('Шкалы'!$M:$M,MATCH($A50&"|"&"Шкала"&"|"&"Оборудование"&"|"&5,'Шкалы'!$U:$U,0)),"") -> 0.19 | G50: =IFERROR(INDEX('Шкалы'!$M:$M,MATCH($A50&"|"&"Шкала"&"|"&"Оборудование"&"|"&6,'Шкалы'!$U:$U,0)),"") -> 0.2 | H50: =IFERROR(INDEX('Шкалы'!$B:$B,MATCH($A50,'Шкалы'!$A:$A,0)),"") -> Заруб
A51: =$W$16 -> CLIPSOMAC, Алжир | B51: =IFERROR(INDEX('Шкалы'!$M:$M,MATCH($A51&"|"&"Шкала"&"|"&"Оборудование"&"|"&1,'Шкалы'!$U:$U,0)),"") -> 0.14 | C51: =IFERROR(INDEX('Шкалы'!$M:$M,MATCH($A51&"|"&"Шкала"&"|"&"Оборудование"&"|"&2,'Шкалы'!$U:$U,0)),"") -> 0.16 | D51: =IFERROR(INDEX('Шкалы'!$M:$M,MATCH($A51&"|"&"Шкала"&"|"&"Оборудование"&"|"&3,'Шкалы'!$U:$U,0)),"") -> 0.17 | E51: =IFERROR(INDEX('Шкалы'!$M:$M,MATCH($A51&"|"&"Шкала"&"|"&"Оборудование"&"|"&4,'Шкалы'!$U:$U,0)),"") -> 0.18 | F51: =IFERROR(INDEX('Шкалы'!$M:$M,MATCH($A51&"|"&"Шкала"&"|"&"Оборудование"&"|"&5,'Шкалы'!$U:$U,0)),"") -> 0.19 | G51: =IFERROR(INDEX('Шкалы'!$M:$M,MATCH($A51&"|"&"Шкала"&"|"&"Оборудование"&"|"&6,'Шкалы'!$U:$U,0)),"") -> 0.2 | H51: =IFERROR(INDEX('Шкалы'!$B:$B,MATCH($A51,'Шкалы'!$A:$A,0)),"") -> Заруб
A52: =$W$17 -> Tida Tech, Таиланд | B52: =IFERROR(INDEX('Шкалы'!$M:$M,MATCH($A52&"|"&"Шкала"&"|"&"Оборудование"&"|"&1,'Шкалы'!$U:$U,0)),"") -> 0.14 | C52: =IFERROR(INDEX('Шкалы'!$M:$M,MATCH($A52&"|"&"Шкала"&"|"&"Оборудование"&"|"&2,'Шкалы'!$U:$U,0)),"") -> 0.16 | D52: =IFERROR(INDEX('Шкалы'!$M:$M,MATCH($A52&"|"&"Шкала"&"|"&"Оборудование"&"|"&3,'Шкалы'!$U:$U,0)),"") -> 0.17 | E52: =IFERROR(INDEX('Шкалы'!$M:$M,MATCH($A52&"|"&"Шкала"&"|"&"Оборудование"&"|"&4,'Шкалы'!$U:$U,0)),"") -> 0.18 | F52: =IFERROR(INDEX('Шкалы'!$M:$M,MATCH($A52&"|"&"Шкала"&"|"&"Оборудование"&"|"&5,'Шкалы'!$U:$U,0)),"") -> 0.19 | G52: =IFERROR(INDEX('Шкалы'!$M:$M,MATCH($A52&"|"&"Шкала"&"|"&"Оборудование"&"|"&6,'Шкалы'!$U:$U,0)),"") -> 0.2 | H52: =IFERROR(INDEX('Шкалы'!$B:$B,MATCH($A52,'Шкалы'!$A:$A,0)),"") -> Заруб
A53: =$W$18 -> Ari Makina, Турция | B53: =IFERROR(INDEX('Шкалы'!$M:$M,MATCH($A53&"|"&"Шкала"&"|"&"Оборудование"&"|"&1,'Шкалы'!$U:$U,0)),"") -> 0.14 | C53: =IFERROR(INDEX('Шкалы'!$M:$M,MATCH($A53&"|"&"Шкала"&"|"&"Оборудование"&"|"&2,'Шкалы'!$U:$U,0)),"") -> 0.16 | D53: =IFERROR(INDEX('Шкалы'!$M:$M,MATCH($A53&"|"&"Шкала"&"|"&"Оборудование"&"|"&3,'Шкалы'!$U:$U,0)),"") -> 0.17 | E53: =IFERROR(INDEX('Шкалы'!$M:$M,MATCH($A53&"|"&"Шкала"&"|"&"Оборудование"&"|"&4,'Шкалы'!$U:$U,0)),"") -> 0.18 | F53: =IFERROR(INDEX('Шкалы'!$M:$M,MATCH($A53&"|"&"Шкала"&"|"&"Оборудование"&"|"&5,'Шкалы'!$U:$U,0)),"") -> 0.19 | G53: =IFERROR(INDEX('Шкалы'!$M:$M,MATCH($A53&"|"&"Шкала"&"|"&"Оборудование"&"|"&6,'Шкалы'!$U:$U,0)),"") -> 0.2 | H53: =IFERROR(INDEX('Шкалы'!$B:$B,MATCH($A53,'Шкалы'!$A:$A,0)),"") -> Заруб
A54: =$W$19 -> Кабири Хучанд ООО, Таджикистан | B54: =IFERROR(INDEX('Шкалы'!$M:$M,MATCH($A54&"|"&"Шкала"&"|"&"Оборудование"&"|"&1,'Шкалы'!$U:$U,0)),"") -> 0.14 | C54: =IFERROR(INDEX('Шкалы'!$M:$M,MATCH($A54&"|"&"Шкала"&"|"&"Оборудование"&"|"&2,'Шкалы'!$U:$U,0)),"") -> 0.16 | D54: =IFERROR(INDEX('Шкалы'!$M:$M,MATCH($A54&"|"&"Шкала"&"|"&"Оборудование"&"|"&3,'Шкалы'!$U:$U,0)),"") -> 0.17 | E54: =IFERROR(INDEX('Шкалы'!$M:$M,MATCH($A54&"|"&"Шкала"&"|"&"Оборудование"&"|"&4,'Шкалы'!$U:$U,0)),"") -> 0.18 | F54: =IFERROR(INDEX('Шкалы'!$M:$M,MATCH($A54&"|"&"Шкала"&"|"&"Оборудование"&"|"&5,'Шкалы'!$U:$U,0)),"") -> 0.19 | G54: =IFERROR(INDEX('Шкалы'!$M:$M,MATCH($A54&"|"&"Шкала"&"|"&"Оборудование"&"|"&6,'Шкалы'!$U:$U,0)),"") -> 0.2 | H54: =IFERROR(INDEX('Шкалы'!$B:$B,MATCH($A54,'Шкалы'!$A:$A,0)),"") -> Заруб
A55: =$W$20 -> Flexo Food , Грузия | B55: =IFERROR(INDEX('Шкалы'!$M:$M,MATCH($A55&"|"&"Шкала"&"|"&"Оборудование"&"|"&1,'Шкалы'!$U:$U,0)),"") -> 0.14 | C55: =IFERROR(INDEX('Шкалы'!$M:$M,MATCH($A55&"|"&"Шкала"&"|"&"Оборудование"&"|"&2,'Шкалы'!$U:$U,0)),"") -> 0.16 | D55: =IFERROR(INDEX('Шкалы'!$M:$M,MATCH($A55&"|"&"Шкала"&"|"&"Оборудование"&"|"&3,'Шкалы'!$U:$U,0)),"") -> 0.17 | E55: =IFERROR(INDEX('Шкалы'!$M:$M,MATCH($A55&"|"&"Шкала"&"|"&"Оборудование"&"|"&4,'Шкалы'!$U:$U,0)),"") -> 0.18 | F55: =IFERROR(INDEX('Шкалы'!$M:$M,MATCH($A55&"|"&"Шкала"&"|"&"Оборудование"&"|"&5,'Шкалы'!$U:$U,0)),"") -> 0.19 | G55: =IFERROR(INDEX('Шкалы'!$M:$M,MATCH($A55&"|"&"Шкала"&"|"&"Оборудование"&"|"&6,'Шкалы'!$U:$U,0)),"") -> 0.2 | H55: =IFERROR(INDEX('Шкалы'!$B:$B,MATCH($A55,'Шкалы'!$A:$A,0)),"") -> Заруб
A56: =$W$21 -> Гинап, Армения | B56: =IFERROR(INDEX('Шкалы'!$M:$M,MATCH($A56&"|"&"Шкала"&"|"&"Оборудование"&"|"&1,'Шкалы'!$U:$U,0)),"") -> 0.14 | C56: =IFERROR(INDEX('Шкалы'!$M:$M,MATCH($A56&"|"&"Шкала"&"|"&"Оборудование"&"|"&2,'Шкалы'!$U:$U,0)),"") -> 0.16 | D56: =IFERROR(INDEX('Шкалы'!$M:$M,MATCH($A56&"|"&"Шкала"&"|"&"Оборудование"&"|"&3,'Шкалы'!$U:$U,0)),"") -> 0.17 | E56: =IFERROR(INDEX('Шкалы'!$M:$M,MATCH($A56&"|"&"Шкала"&"|"&"Оборудование"&"|"&4,'Шкалы'!$U:$U,0)),"") -> 0.18 | F56: =IFERROR(INDEX('Шкалы'!$M:$M,MATCH($A56&"|"&"Шкала"&"|"&"Оборудование"&"|"&5,'Шкалы'!$U:$U,0)),"") -> 0.19 | G56: =IFERROR(INDEX('Шкалы'!$M:$M,MATCH($A56&"|"&"Шкала"&"|"&"Оборудование"&"|"&6,'Шкалы'!$U:$U,0)),"") -> 0.2 | H56: =IFERROR(INDEX('Шкалы'!$B:$B,MATCH($A56,'Шкалы'!$A:$A,0)),"") -> Заруб

Sheet Блоки
A1: БЛОКИ ДИЛЕРОВ — копия исходных вкладок, для сверки с оригиналом
A2: Каждый дилер — блок строк, над ним строка-маркер (ячейка A начинается с «### ДИЛЕР»). Строки блока сгруппированы: сворачиваются кнопкой слева.
A3: Править шкалы нужно на листе «Шкалы» (плоская таблица) — именно её читает калькулятор. Лист «Витрина» показывает те же данные глазами.
A4: Этот лист калькулятор разбирает только как запасной вариант — если листа «Шкалы» в файле не окажется. Формулы, форматы, объединённые ячейки и оформление перенесены из исходника 1:1.
A5: Собрано автоматически из legacy/scales_multisheet_2026.xlsx (21 вкладок → 18 блоков) • tools/consolidate_scales.py • 2026-10-02
A7: СОДЕРЖАНИЕ — клик по строке переносит к блоку дилера
A8: 1 • КОМПО Технолоджис • РФ • вкладка «КТ» • блок в строке 28
A9: 2 • НоваПак • РФ • вкладка «НоваПак» • блок в строке 70
A10: 3 • КСП (КОМПО-СП) • РФ • вкладка «КСП» • блок в строке 112
A11: 4 • Богатовъ Торговый Дом, Челябинск • РФ • вкладка «Богатовъ Торговый Дом, Челябинс» • блок в строке 155
A12: 5 • ASIAN BUSINESS SOLUTIONS, Узбекистан • Заруб • вкладка «ABS» • блок в строке 197
A13: 6 • Deling food • Заруб • вкладка «Deling fod» • блок в строке 234
... A28: ### ДИЛЕР 1/18 • КОМПО Технолоджис • РФ (отчётность за квартал) • вкладка «КТ» • исходные строки 1–39 (A1:K39)
D31: Выручка 2024 | E31: Выручка 2025 | F31: План 2026 | G31: Прирост П/Ф | H31: Размер бонуса по итогам 2026 г | I31: Скидка в 1 кв. 2026 ф.г.*
C32: КОМПО Технолоджис | D32: 4164812 | E32: 4121760 | F32: =SUM(F33:F35) -> 4142912 | G32: =F32/E32-1 -> 0.0051317859
C33: Сервис | D33: 346883 | E33: 448343 | F33: 480438 | H33: 0.01 | I33: 0.3
C34: Оборудование | D34: 2205660 | E34: 1710368 | F34: 2020593.8 | H34: 0.015 | I34: 0.19
C35: Расходные материалы | D35: 1612269 | E35: 1963049 | F35: 1641880.2 | H35: 0.005 | I35: 0.06
C36: * - скидка согласно правил работы ТПС на 2026 ф.г.
C37: Ретробонус насчитывается и выплачивается по каждому направлению отдельно при выполнении плана 100% и более. Каждое направление имеет свой % бонусирования. Бонусирование вступает в силу к расчету только при условии выполнения плана ИТОГО на 95%. При отсутствии просроченной Дебиторской Задолженности бонус выплачивается в полном размере.
C39: 3.1.1. Система предоставления скидок
C40: ОБЪЕМ закупок оборудования (тысяч евро) за 3 месяца (квартал) | E40: до 75 | F40: 75-114 | G40: 115-149 | H40: 150-189 | I40: 190-224 | J40: 225 и более
C41: 1 Базовое вознаграждение за Дилерский договор | D41: Скидка % | E41: 6 | F41: 6 | G41: 6 | H41: 6 | I41: 6 | J41: 6
C42: 2.1.1. Сервисный центр | D42: Скидка % | E42: 6 | F42: 6 | G42: 6 | H42: 6 | I42: 6 | J42: 6
C43: 2.1.2. Сервисный центр - гарантийное обслуживание | D43: Скидка % | E43: 1 | F43: 1 | G43: 1 | H43: 1 | I43: 1 | J43: 1
B44: ??? | C44: 2.3 Наличие минимальных складских остатков по оборудованию | D44: Ретро-скидка % | E44: 1 | F44: 1 | G44: 1 | H44: 1 | I44: 1 | J44: 1
C45: 3 Объем закупок МП | D45: скидка будущих периодов % | E45: 0 | F45: 1 | G45: 2 | H45: 3 | I45: 4 | J45: 5
C46: ИТОГО по МП: | E46: =SUM(E41:E45) -> 14 | F46: =SUM(F41:F45) -> 15 | G46: =SUM(G41:G45) -> 16 | H46: =SUM(H41:H45) -> 17 | I46: =SUM(I41:I45) -> 18 | J46: =SUM(J41:J45) -> 19
C47: ОБЪЕМ закупок РМ (тысяч евро) за 3 месяца (квартал) | E47: до 75 | F47: 75-115 | G47: 115-150 | H47: 150-190 | I47: 190-225 | J47: 225 и более
C48: Наличие минимальных складских остатков по РМ (синхронизация отчета по остаткам с 1С КОМПО) | D48: Скидка будущих периодов, % | E48: 1 | F48: 1 | G48: 1 | H48: 1 | I48: 1 | J48: 1
C49: Объем закупок РМ | D49: скидка будущих периодов, % | E49: 0 | F49: 1 | G49: 2 | H49: 3 | I49: 4 | J49: 5
C51: СИСТЕМА РАСЧЕТА СКИДКИ ПО ЗАПЧАСТЯМ
D52: Отношение объема закупок ЗЧ к парку оборудования, евро / ед. об. | F52: Процент скидки
D53: без статуса партнера | F53: 0.15
C54: диапазон отношения | D54: 0 | E54: 500 | F54: 0.19
C55: диапазон отношения | D55: 501 | E55: 1000 | F55: 0.21
C56: диапазон отношения | D56: 1001 | E56: 1800 | F56: 0.23
C57: диапазон отношения | D57: 1801 | E57: 2400 | F57: 0.25
C58: диапазон отношения | D58: 2401 | E58: 3000 | F58: 0.27
C59: диапазон отношения | D59: 3001 | F59: 0.3
C60: Система контроля как и система бонусирования работает ежеквартально (до 5го числа месяца, следующего за отчетным кварталом), кроме годового бонуса.
C62: Система контроля квартального и годового бонусирования
C63: уменьшение бонуса за невыполнение минимальных квартальных показателей закупок по МП (при наличии установленного показателя) | D63: скидка будущих периодов квартала, % | E63: 1
C64: уменьшение бонуса за невыполнение минимальных квартальных показателей закупок по РМ (при наличии установленного показателя) | D64: скидка будущих периодов квартала, % | E64: 1
C65: за несвоевременное предоставление Скользящего прогноза | D65: скидка будущих периодов квартала, % | E65: 0.5
C66: уменьшение бонуса за отказ от зарезервированного оборудования | D66: скидка будущих периодов квартала, % | E66: 0.5
C67: Выполнение плановых показателей года ИТОГО | D67: ретро-бонус % | E67: 1
A70: ### ДИЛЕР 2/18 • НоваПак • РФ (отчётность за квартал) • вкладка «НоваПак» • исходные строки 1–39 (A1:K39)
D73: Выручка 2024 | E73: Выручка 2025 | F73: План 2026 | G73: Прирост П/Ф | H73: Размер бонуса по итогам 2026 г | I73: Скидка в 1 кв. 2026 ф.г.*
C74: НоваПак | D74: 1609061 | E74: 1299534 | F74: =SUM(F75:F77) -> 1812000 | G74: =F74/E74-1 -> 0.39434597
C75: Сервис | D75: 233434 | E75: 302280 | F75: 365000 | H75: 0.01 | I75: 0.27
C76: Оборудование | D76: 912543 | E76: 401117 | F76: 787000 | H76: 0.015 | I76: 0.15
C77: Расходные материалы | D77: 463084 | E77: 596137 | F77: 660000 | H77: 0.005 | I77: 0.02
C78: * - скидка согласно правил работы ТПС на 2026 ф.г.
C79: Ретробонус насчитывается и выплачивается по каждому направлению отдельно при выполнении плана 100% и более. Каждое направление имеет свой % бонусирования. Бонусирование вступает в силу к расчету только при условии выполнения плана ИТОГО на 95%. При отсутствии просроченной Дебиторской Задолженности бонус выплачивается в полном размере.
C81: 3.1.1. Система предоставления скидок
C82: ОБЪЕМ закупок оборудования (тысяч евро) за 3 месяца (квартал) | E82: до 75 | F82: 75-114 | G82: 115-149 | H82: 150-189 | I82: 190-224 | J82: 225 и более
C83: 1 Базовое вознаграждение за Дилерский договор | D83: Скидка % | E83: 6 | F83: 6 | G83: 6 | H83: 6 | I83: 6 | J83: 6
C84: 2.1.1. Сервисный центр | D84: Скидка % | E84: 6 | F84: 6 | G84: 6 | H84: 6 | I84: 6 | J84: 6
C85: 2.1.2. Сервисный центр - гарантийное обслуживание | D85: Скидка % | E85: 1 | F85: 1 | G85: 1 | H85: 1 | I85: 1 | J85: 1
C86: 2.3 Наличие минимальных складских остатков по оборудованию | D86: Ретро-скидка % | E86: 1 | F86: 1 | G86: 1 | H86: 1 | I86: 1 | J86: 1
C87: 3 Объем закупок МП | D87: скидка будущих периодов % | E87: 0 | F87: 1 | G87: 2 | H87: 3 | I87: 4 | J87: 5
C88: ИТОГО по МП: | E88: =SUM(E83:E87) -> 14 | F88: =SUM(F83:F87) -> 15 | G88: =SUM(G83:G87) -> 16 | H88: =SUM(H83:H87) -> 17 | I88: =SUM(I83:I87) -> 18 | J88: =SUM(J83:J87) -> 19
C89: ОБЪЕМ закупок РМ (тысяч евро) за 3 месяца (квартал) | E89: до 75 | F89: 75-115 | G89: 115-150 | H89: 150-190 | I89: 190-225 | J89: 225 и более
C90: Наличие минимальных складских остатков по РМ (синхронизация отчета по остаткам с 1С КОМПО) | D90: Скидка будущих периодов, % | E90: 1 | F90: 1 | G90: 1 | H90: 1 | I90: 1 | J90: 1
C91: Объем закупок РМ | D91: скидка будущих периодов, % | E91: 0 | F91: 1 | G91: 2 | H91: 3 | I91: 4 | J91: 5
C93: СИСТЕМА РАСЧЕТА СКИДКИ ПО ЗАПЧАСТЯМ
D94: Отношение объема закупок ЗЧ к парку оборудования, евро / ед. об. | F94: Процент скидки
D95: без статуса партнера | F95: 0.15
C96: диапазон отношения | D96: 0 | E96: 500 | F96: 0.19
C97: диапазон отношения | D97: 501 | E97: 1000 | F97: 0.21
C98: диапазон отношения | D98: 1001 | E98: 1800 | F98: 0.23
C99: диапазон отношения | D99: 1801 | E99: 2400 | F99: 0.25
C100: диапазон отношения | D100: 2401 | E100: 3000 | F100: 0.27
C101: диапазон отношения | D101: 3001 | F101: 0.3
C102: Система контроля как и система бонусирования работает ежеквартально (до 5го числа месяца, следующего за отчетным кварталом), кроме годового бонуса.
C104: Система контроля квартального и годового бонусирования
C105: уменьшение бонуса за невыполнение минимальных квартальных показателей закупок по МП (при наличии установленного показателя) | D105: скидка будущих периодов квартала, % | E105: 1
C106: уменьшение бонуса за невыполнение минимальных квартальных показателей закупок по РМ (при наличии установленного показателя) | D106: скидка будущих периодов квартала, % | E106: 1
C107: за несвоевременное предоставление Скользящего прогноза | D107: скидка будущих периодов квартала, % | E107: 0.5
C108: уменьшение бонуса за отказ от зарезервированного оборудования | D108: скидка будущих периодов квартала, % | E108: 0.5
C109: Выполнение плановых показателей года ИТОГО | D109: ретро-бонус % | E109: 1
A112: ### ДИЛЕР 3/18 • КСП (КОМПО-СП) • РФ (отчётность за квартал) • вкладка «КСП» • исходные строки 1–40 (A1:J40)
D115: Выручка 2024 | E115: Выручка 2025 | F115: План 2026 | G115: Прирост П/Ф | H115: Размер бонуса по итогам 2026 г | I115: Скидка в 1 кв. 2026 ф.г.*
C116: КСП (КОМПО-СП) | D116: 1548968 | E116: 1948199 | F116: =SUM(F117:F119) -> 2104000 | G116: =F116/E116-1 -> 0.07997181
C117: Сервис | D117: 218223 | E117: 246890 | F117: 305000 | H117: 0.01 | I117: 0.23
C118: Оборудование | D118: 717996 | E118: 974706 | F118: 999000 | H118: 0.015 | I118: 0.17
C119: Расходные материалы | D119: 612749 | E119: 726603 | F119: 800000 | H119: 0.005 | I119: 0.03
C120: * - скидка согласно правил работы ТПС на 2026 ф.г.
C121: Ретробонус насчитывается и выплачивается по каждому направлению отдельно при выполнении плана 100% и более. Каждое направление имеет свой % бонусирования. Бонусирование вступает в силу к расчету только при условии выполнения плана ИТОГО на 95%. При отсутствии просроченной Дебиторской Задолженности бонус выплачивается в полном размере.
C123: 3.1.1. Система предоставления скидок
C124: ОБЪЕМ закупок оборудования (тысяч евро) за 3 месяца (квартал) | E124: до 75 | F124: 75-114 | G124: 115-149 | H124: 150-189 | I124: 190-224 | J124: 225 и более
C125: 1 Базовое вознаграждение за Дилерский договор | D125: Скидка % | E125: 6 | F125: 6 | G125: 6 | H125: 6 | I125: 6 | J125: 6
C126: 2.1.1. Сервисный центр | D126: Скидка % | E126: 6 | F126: 6 | G126: 6 | H126: 6 | I126: 6 | J126: 6
C127: 2.1.2. Сервисный центр - гарантийное обслуживание | D127: Скидка % | E127: 1 | F127: 1 | G127: 1 | H127: 1 | I127: 1 | J127: 1
C128: 2.3 Наличие минимальных складских остатков по оборудованию | D128: Ретро-скидка % | E128: 1 | F128: 1 | G128: 1 | H128: 1 | I128: 1 | J128: 1
C129: 3 Объем закупок МП | D129: скидка будущих периодов % | E129: 0 | F129: 1 | G129: 2 | H129: 3 | I129: 4 | J129: 5
C130: ИТОГО по МП: | E130: =SUM(E125:E129) -> 14 | F130: =SUM(F125:F129) -> 15 | G130: =SUM(G125:G129) -> 16 | H130: =SUM(H125:H129) -> 17 | I130: =SUM(I125:I129) -> 18 | J130: =SUM(J125:J129) -> 19
C131: ОБЪЕМ закупок РМ (тысяч евро) за 3 месяца (квартал) | E131: до 75 | F131: 75-115 | G131: 115-150 | H131: 150-190 | I131: 190-225 | J131: 225 и более
C132: Наличие минимальных складских остатков по РМ (синхронизация отчета по остаткам с 1С КОМПО) | D132: Скидка будущих периодов, % | E132: 1 | F132: 1 | G132: 1 | H132: 1 | I132: 1 | J132: 1
...
